{
  "portfolioName" : "diverse",
  "symbols" : [ "USO", "GLD", "MUB", "VCLT", "LQD", "IGLB", "XOM", "SPY", "QQQ", "VXUS" ],
  "startWeights" : {
    "USO" : 0.1,
    "GLD" : 0.1,
    "MUB" : 0.1,
    "VCLT" : 0.1,
    "LQD" : 0.1,
    "IGLB" : 0.1,
    "XOM" : 0.1,
    "SPY" : 0.1,
    "QQQ" : 0.1,
    "VXUS" : 0.1
  },
  "initialUtility" : 0.14434478380960278,
  "epochs" : [ {
    "epoch" : 0,
    "startWeights" : {
      "USO" : 0.1,
      "GLD" : 0.1,
      "MUB" : 0.1,
      "VCLT" : 0.1,
      "LQD" : 0.1,
      "IGLB" : 0.1,
      "XOM" : 0.1,
      "SPY" : 0.1,
      "QQQ" : 0.1,
      "VXUS" : 0.1
    },
    "startUtility" : 0.14434478380960278,
    "feasibleCount" : 10,
    "variants" : [ {
      "symbol" : "USO",
      "weights" : {
        "USO" : 0.11,
        "GLD" : 0.098889,
        "MUB" : 0.098889,
        "VCLT" : 0.098889,
        "LQD" : 0.098889,
        "IGLB" : 0.098889,
        "XOM" : 0.098889,
        "SPY" : 0.098889,
        "QQQ" : 0.098889,
        "VXUS" : 0.098889
      },
      "utility" : 0.1453758039616764,
      "delta" : 0.001031020152073625
    }, {
      "symbol" : "GLD",
      "weights" : {
        "USO" : 0.098889,
        "GLD" : 0.11,
        "MUB" : 0.098889,
        "VCLT" : 0.098889,
        "LQD" : 0.098889,
        "IGLB" : 0.098889,
        "XOM" : 0.098889,
        "SPY" : 0.098889,
        "QQQ" : 0.098889,
        "VXUS" : 0.098889
      },
      "utility" : 0.14514668373179365,
      "delta" : 8.01899922190874E-4
    }, {
      "symbol" : "MUB",
      "weights" : {
        "USO" : 0.098889,
        "GLD" : 0.098889,
        "MUB" : 0.11,
        "VCLT" : 0.098889,
        "LQD" : 0.098889,
        "IGLB" : 0.098889,
        "XOM" : 0.098889,
        "SPY" : 0.098889,
        "QQQ" : 0.098889,
        "VXUS" : 0.098889
      },
      "utility" : 0.14302276785190318,
      "delta" : -0.001322015957699596
    }, {
      "symbol" : "VCLT",
      "weights" : {
        "USO" : 0.098889,
        "GLD" : 0.098889,
        "MUB" : 0.098889,
        "VCLT" : 0.11,
        "LQD" : 0.098889,
        "IGLB" : 0.098889,
        "XOM" : 0.098889,
        "SPY" : 0.098889,
        "QQQ" : 0.098889,
        "VXUS" : 0.098889
      },
      "utility" : 0.1431041045118145,
      "delta" : -0.0012406792977882886
    }, {
      "symbol" : "LQD",
      "weights" : {
        "USO" : 0.098889,
        "GLD" : 0.098889,
        "MUB" : 0.098889,
        "VCLT" : 0.098889,
        "LQD" : 0.11,
        "IGLB" : 0.098889,
        "XOM" : 0.098889,
        "SPY" : 0.098889,
        "QQQ" : 0.098889,
        "VXUS" : 0.098889
      },
      "utility" : 0.14312168131108513,
      "delta" : -0.0012231024985176475
    }, {
      "symbol" : "IGLB",
      "weights" : {
        "USO" : 0.098889,
        "GLD" : 0.098889,
        "MUB" : 0.098889,
        "VCLT" : 0.098889,
        "LQD" : 0.098889,
        "IGLB" : 0.11,
        "XOM" : 0.098889,
        "SPY" : 0.098889,
        "QQQ" : 0.098889,
        "VXUS" : 0.098889
      },
      "utility" : 0.14309387908968768,
      "delta" : -0.0012509047199150969
    }, {
      "symbol" : "XOM",
      "weights" : {
        "USO" : 0.098889,
        "GLD" : 0.098889,
        "MUB" : 0.098889,
        "VCLT" : 0.098889,
        "LQD" : 0.098889,
        "IGLB" : 0.098889,
        "XOM" : 0.11,
        "SPY" : 0.098889,
        "QQQ" : 0.098889,
        "VXUS" : 0.098889
      },
      "utility" : 0.14516761019982566,
      "delta" : 8.228263902228805E-4
    }, {
      "symbol" : "SPY",
      "weights" : {
        "USO" : 0.098889,
        "GLD" : 0.098889,
        "MUB" : 0.098889,
        "VCLT" : 0.098889,
        "LQD" : 0.098889,
        "IGLB" : 0.098889,
        "XOM" : 0.098889,
        "SPY" : 0.11,
        "QQQ" : 0.098889,
        "VXUS" : 0.098889
      },
      "utility" : 0.14509148863748808,
      "delta" : 7.467048278853028E-4
    }, {
      "symbol" : "QQQ",
      "weights" : {
        "USO" : 0.098889,
        "GLD" : 0.098889,
        "MUB" : 0.098889,
        "VCLT" : 0.098889,
        "LQD" : 0.098889,
        "IGLB" : 0.098889,
        "XOM" : 0.098889,
        "SPY" : 0.098889,
        "QQQ" : 0.11,
        "VXUS" : 0.098889
      },
      "utility" : 0.14606682206015834,
      "delta" : 0.0017220382505555576
    }, {
      "symbol" : "VXUS",
      "weights" : {
        "USO" : 0.098889,
        "GLD" : 0.098889,
        "MUB" : 0.098889,
        "VCLT" : 0.098889,
        "LQD" : 0.098889,
        "IGLB" : 0.098889,
        "XOM" : 0.098889,
        "SPY" : 0.098889,
        "QQQ" : 0.098889,
        "VXUS" : 0.11
      },
      "utility" : 0.14412986890566765,
      "delta" : -2.1491490393513168E-4
    } ],
    "winner" : "QQQ",
    "endWeights" : {
      "USO" : 0.098889,
      "GLD" : 0.098889,
      "MUB" : 0.098889,
      "VCLT" : 0.098889,
      "LQD" : 0.098889,
      "IGLB" : 0.098889,
      "XOM" : 0.098889,
      "SPY" : 0.098889,
      "QQQ" : 0.11,
      "VXUS" : 0.098889
    },
    "endUtility" : 0.14606682206015834,
    "improvement" : 0.0017220382505555576
  }, {
    "epoch" : 1,
    "startWeights" : {
      "USO" : 0.098889,
      "GLD" : 0.098889,
      "MUB" : 0.098889,
      "VCLT" : 0.098889,
      "LQD" : 0.098889,
      "IGLB" : 0.098889,
      "XOM" : 0.098889,
      "SPY" : 0.098889,
      "QQQ" : 0.11,
      "VXUS" : 0.098889
    },
    "startUtility" : 0.14606682206015834,
    "feasibleCount" : 10,
    "variants" : [ {
      "symbol" : "USO",
      "weights" : {
        "USO" : 0.108889,
        "GLD" : 0.097778,
        "MUB" : 0.097778,
        "VCLT" : 0.097778,
        "LQD" : 0.097778,
        "IGLB" : 0.097778,
        "XOM" : 0.097778,
        "SPY" : 0.097778,
        "QQQ" : 0.108889,
        "VXUS" : 0.097778
      },
      "utility" : 0.14712999490236617,
      "delta" : 0.0010631728422078324
    }, {
      "symbol" : "GLD",
      "weights" : {
        "USO" : 0.097778,
        "GLD" : 0.108889,
        "MUB" : 0.097778,
        "VCLT" : 0.097778,
        "LQD" : 0.097778,
        "IGLB" : 0.097778,
        "XOM" : 0.097778,
        "SPY" : 0.097778,
        "QQQ" : 0.108889,
        "VXUS" : 0.097778
      },
      "utility" : 0.14687560399147723,
      "delta" : 8.087819313188915E-4
    }, {
      "symbol" : "MUB",
      "weights" : {
        "USO" : 0.097778,
        "GLD" : 0.097778,
        "MUB" : 0.108889,
        "VCLT" : 0.097778,
        "LQD" : 0.097778,
        "IGLB" : 0.097778,
        "XOM" : 0.097778,
        "SPY" : 0.097778,
        "QQQ" : 0.108889,
        "VXUS" : 0.097778
      },
      "utility" : 0.1447404487629271,
      "delta" : -0.0013263732972312314
    }, {
      "symbol" : "VCLT",
      "weights" : {
        "USO" : 0.097778,
        "GLD" : 0.097778,
        "MUB" : 0.097778,
        "VCLT" : 0.108889,
        "LQD" : 0.097778,
        "IGLB" : 0.097778,
        "XOM" : 0.097778,
        "SPY" : 0.097778,
        "QQQ" : 0.108889,
        "VXUS" : 0.097778
      },
      "utility" : 0.14481958421537958,
      "delta" : -0.001247237844778759
    }, {
      "symbol" : "LQD",
      "weights" : {
        "USO" : 0.097778,
        "GLD" : 0.097778,
        "MUB" : 0.097778,
        "VCLT" : 0.097778,
        "LQD" : 0.108889,
        "IGLB" : 0.097778,
        "XOM" : 0.097778,
        "SPY" : 0.097778,
        "QQQ" : 0.108889,
        "VXUS" : 0.097778
      },
      "utility" : 0.14483679807780217,
      "delta" : -0.0012300239823561654
    }, {
      "symbol" : "IGLB",
      "weights" : {
        "USO" : 0.097778,
        "GLD" : 0.097778,
        "MUB" : 0.097778,
        "VCLT" : 0.097778,
        "LQD" : 0.097778,
        "IGLB" : 0.108889,
        "XOM" : 0.097778,
        "SPY" : 0.097778,
        "QQQ" : 0.108889,
        "VXUS" : 0.097778
      },
      "utility" : 0.14480851842736697,
      "delta" : -0.0012583036327913633
    }, {
      "symbol" : "XOM",
      "weights" : {
        "USO" : 0.097778,
        "GLD" : 0.097778,
        "MUB" : 0.097778,
        "VCLT" : 0.097778,
        "LQD" : 0.097778,
        "IGLB" : 0.097778,
        "XOM" : 0.108889,
        "SPY" : 0.097778,
        "QQQ" : 0.108889,
        "VXUS" : 0.097778
      },
      "utility" : 0.14691974041577294,
      "delta" : 8.529183556146014E-4
    }, {
      "symbol" : "SPY",
      "weights" : {
        "USO" : 0.097778,
        "GLD" : 0.097778,
        "MUB" : 0.097778,
        "VCLT" : 0.097778,
        "LQD" : 0.097778,
        "IGLB" : 0.097778,
        "XOM" : 0.097778,
        "SPY" : 0.108889,
        "QQQ" : 0.108889,
        "VXUS" : 0.097778
      },
      "utility" : 0.1467731908810571,
      "delta" : 7.063688208987506E-4
    }, {
      "symbol" : "QQQ",
      "weights" : {
        "USO" : 0.097778,
        "GLD" : 0.097778,
        "MUB" : 0.097778,
        "VCLT" : 0.097778,
        "LQD" : 0.097778,
        "IGLB" : 0.097778,
        "XOM" : 0.097778,
        "SPY" : 0.097778,
        "QQQ" : 0.12,
        "VXUS" : 0.097778
      },
      "utility" : 0.14772397456010794,
      "delta" : 0.0016571524999496046
    }, {
      "symbol" : "VXUS",
      "weights" : {
        "USO" : 0.097778,
        "GLD" : 0.097778,
        "MUB" : 0.097778,
        "VCLT" : 0.097778,
        "LQD" : 0.097778,
        "IGLB" : 0.097778,
        "XOM" : 0.097778,
        "SPY" : 0.097778,
        "QQQ" : 0.108889,
        "VXUS" : 0.108889
      },
      "utility" : 0.14583739486992112,
      "delta" : -2.2942719023721914E-4
    } ],
    "winner" : "QQQ",
    "endWeights" : {
      "USO" : 0.097778,
      "GLD" : 0.097778,
      "MUB" : 0.097778,
      "VCLT" : 0.097778,
      "LQD" : 0.097778,
      "IGLB" : 0.097778,
      "XOM" : 0.097778,
      "SPY" : 0.097778,
      "QQQ" : 0.12,
      "VXUS" : 0.097778
    },
    "endUtility" : 0.14772397456010794,
    "improvement" : 0.0016571524999496046
  }, {
    "epoch" : 2,
    "startWeights" : {
      "USO" : 0.097778,
      "GLD" : 0.097778,
      "MUB" : 0.097778,
      "VCLT" : 0.097778,
      "LQD" : 0.097778,
      "IGLB" : 0.097778,
      "XOM" : 0.097778,
      "SPY" : 0.097778,
      "QQQ" : 0.12,
      "VXUS" : 0.097778
    },
    "startUtility" : 0.14772397456010794,
    "feasibleCount" : 10,
    "variants" : [ {
      "symbol" : "USO",
      "weights" : {
        "USO" : 0.107778,
        "GLD" : 0.096667,
        "MUB" : 0.096667,
        "VCLT" : 0.096667,
        "LQD" : 0.096667,
        "IGLB" : 0.096667,
        "XOM" : 0.096667,
        "SPY" : 0.096667,
        "QQQ" : 0.118889,
        "VXUS" : 0.096667
      },
      "utility" : 0.1488500069989666,
      "delta" : 0.0011260324388586707
    }, {
      "symbol" : "GLD",
      "weights" : {
        "USO" : 0.096667,
        "GLD" : 0.107778,
        "MUB" : 0.096667,
        "VCLT" : 0.096667,
        "LQD" : 0.096667,
        "IGLB" : 0.096667,
        "XOM" : 0.096667,
        "SPY" : 0.096667,
        "QQQ" : 0.118889,
        "VXUS" : 0.096667
      },
      "utility" : 0.1485485216270854,
      "delta" : 8.245470669774602E-4
    }, {
      "symbol" : "MUB",
      "weights" : {
        "USO" : 0.096667,
        "GLD" : 0.096667,
        "MUB" : 0.107778,
        "VCLT" : 0.096667,
        "LQD" : 0.096667,
        "IGLB" : 0.096667,
        "XOM" : 0.096667,
        "SPY" : 0.096667,
        "QQQ" : 0.118889,
        "VXUS" : 0.096667
      },
      "utility" : 0.14640056886253863,
      "delta" : -0.0013234056975693076
    }, {
      "symbol" : "VCLT",
      "weights" : {
        "USO" : 0.096667,
        "GLD" : 0.096667,
        "MUB" : 0.096667,
        "VCLT" : 0.107778,
        "LQD" : 0.096667,
        "IGLB" : 0.096667,
        "XOM" : 0.096667,
        "SPY" : 0.096667,
        "QQQ" : 0.118889,
        "VXUS" : 0.096667
      },
      "utility" : 0.14647707943300525,
      "delta" : -0.0012468951271026874
    }, {
      "symbol" : "LQD",
      "weights" : {
        "USO" : 0.096667,
        "GLD" : 0.096667,
        "MUB" : 0.096667,
        "VCLT" : 0.096667,
        "LQD" : 0.107778,
        "IGLB" : 0.096667,
        "XOM" : 0.096667,
        "SPY" : 0.096667,
        "QQQ" : 0.118889,
        "VXUS" : 0.096667
      },
      "utility" : 0.1464947269759253,
      "delta" : -0.0012292475841826356
    }, {
      "symbol" : "IGLB",
      "weights" : {
        "USO" : 0.096667,
        "GLD" : 0.096667,
        "MUB" : 0.096667,
        "VCLT" : 0.096667,
        "LQD" : 0.096667,
        "IGLB" : 0.107778,
        "XOM" : 0.096667,
        "SPY" : 0.096667,
        "QQQ" : 0.118889,
        "VXUS" : 0.096667
      },
      "utility" : 0.14646571942307723,
      "delta" : -0.001258255137030706
    }, {
      "symbol" : "XOM",
      "weights" : {
        "USO" : 0.096667,
        "GLD" : 0.096667,
        "MUB" : 0.096667,
        "VCLT" : 0.096667,
        "LQD" : 0.096667,
        "IGLB" : 0.096667,
        "XOM" : 0.107778,
        "SPY" : 0.096667,
        "QQQ" : 0.118889,
        "VXUS" : 0.096667
      },
      "utility" : 0.14863361178275902,
      "delta" : 9.096372226510829E-4
    }, {
      "symbol" : "SPY",
      "weights" : {
        "USO" : 0.096667,
        "GLD" : 0.096667,
        "MUB" : 0.096667,
        "VCLT" : 0.096667,
        "LQD" : 0.096667,
        "IGLB" : 0.096667,
        "XOM" : 0.096667,
        "SPY" : 0.107778,
        "QQQ" : 0.118889,
        "VXUS" : 0.096667
      },
      "utility" : 0.14842004810771553,
      "delta" : 6.960735476075897E-4
    }, {
      "symbol" : "QQQ",
      "weights" : {
        "USO" : 0.096667,
        "GLD" : 0.096667,
        "MUB" : 0.096667,
        "VCLT" : 0.096667,
        "LQD" : 0.096667,
        "IGLB" : 0.096667,
        "XOM" : 0.096667,
        "SPY" : 0.096667,
        "QQQ" : 0.13,
        "VXUS" : 0.096667
      },
      "utility" : 0.149358814392407,
      "delta" : 0.001634839832299062
    }, {
      "symbol" : "VXUS",
      "weights" : {
        "USO" : 0.096667,
        "GLD" : 0.096667,
        "MUB" : 0.096667,
        "VCLT" : 0.096667,
        "LQD" : 0.096667,
        "IGLB" : 0.096667,
        "XOM" : 0.096667,
        "SPY" : 0.096667,
        "QQQ" : 0.118889,
        "VXUS" : 0.107778
      },
      "utility" : 0.1474900315058661,
      "delta" : -2.3394305424184747E-4
    } ],
    "winner" : "QQQ",
    "endWeights" : {
      "USO" : 0.096667,
      "GLD" : 0.096667,
      "MUB" : 0.096667,
      "VCLT" : 0.096667,
      "LQD" : 0.096667,
      "IGLB" : 0.096667,
      "XOM" : 0.096667,
      "SPY" : 0.096667,
      "QQQ" : 0.13,
      "VXUS" : 0.096667
    },
    "endUtility" : 0.149358814392407,
    "improvement" : 0.001634839832299062
  }, {
    "epoch" : 3,
    "startWeights" : {
      "USO" : 0.096667,
      "GLD" : 0.096667,
      "MUB" : 0.096667,
      "VCLT" : 0.096667,
      "LQD" : 0.096667,
      "IGLB" : 0.096667,
      "XOM" : 0.096667,
      "SPY" : 0.096667,
      "QQQ" : 0.13,
      "VXUS" : 0.096667
    },
    "startUtility" : 0.149358814392407,
    "feasibleCount" : 10,
    "variants" : [ {
      "symbol" : "USO",
      "weights" : {
        "USO" : 0.106667,
        "GLD" : 0.095556,
        "MUB" : 0.095556,
        "VCLT" : 0.095556,
        "LQD" : 0.095556,
        "IGLB" : 0.095556,
        "XOM" : 0.095556,
        "SPY" : 0.095556,
        "QQQ" : 0.128889,
        "VXUS" : 0.095556
      },
      "utility" : 0.15051600211129543,
      "delta" : 0.001157187718888425
    }, {
      "symbol" : "GLD",
      "weights" : {
        "USO" : 0.095556,
        "GLD" : 0.106667,
        "MUB" : 0.095556,
        "VCLT" : 0.095556,
        "LQD" : 0.095556,
        "IGLB" : 0.095556,
        "XOM" : 0.095556,
        "SPY" : 0.095556,
        "QQQ" : 0.128889,
        "VXUS" : 0.095556
      },
      "utility" : 0.1501813193751377,
      "delta" : 8.22504982730704E-4
    }, {
      "symbol" : "MUB",
      "weights" : {
        "USO" : 0.095556,
        "GLD" : 0.095556,
        "MUB" : 0.106667,
        "VCLT" : 0.095556,
        "LQD" : 0.095556,
        "IGLB" : 0.095556,
        "XOM" : 0.095556,
        "SPY" : 0.095556,
        "QQQ" : 0.128889,
        "VXUS" : 0.095556
      },
      "utility" : 0.14803310912257792,
      "delta" : -0.001325705269829086
    }, {
      "symbol" : "VCLT",
      "weights" : {
        "USO" : 0.095556,
        "GLD" : 0.095556,
        "MUB" : 0.095556,
        "VCLT" : 0.106667,
        "LQD" : 0.095556,
        "IGLB" : 0.095556,
        "XOM" : 0.095556,
        "SPY" : 0.095556,
        "QQQ" : 0.128889,
        "VXUS" : 0.095556
      },
      "utility" : 0.1481007636742398,
      "delta" : -0.001258050718167203
    }, {
      "symbol" : "LQD",
      "weights" : {
        "USO" : 0.095556,
        "GLD" : 0.095556,
        "MUB" : 0.095556,
        "VCLT" : 0.095556,
        "LQD" : 0.106667,
        "IGLB" : 0.095556,
        "XOM" : 0.095556,
        "SPY" : 0.095556,
        "QQQ" : 0.128889,
        "VXUS" : 0.095556
      },
      "utility" : 0.1481210976544571,
      "delta" : -0.0012377167379498955
    }, {
      "symbol" : "IGLB",
      "weights" : {
        "USO" : 0.095556,
        "GLD" : 0.095556,
        "MUB" : 0.095556,
        "VCLT" : 0.095556,
        "LQD" : 0.095556,
        "IGLB" : 0.106667,
        "XOM" : 0.095556,
        "SPY" : 0.095556,
        "QQQ" : 0.128889,
        "VXUS" : 0.095556
      },
      "utility" : 0.14808914318428304,
      "delta" : -0.0012696712081239625
    }, {
      "symbol" : "XOM",
      "weights" : {
        "USO" : 0.095556,
        "GLD" : 0.095556,
        "MUB" : 0.095556,
        "VCLT" : 0.095556,
        "LQD" : 0.095556,
        "IGLB" : 0.095556,
        "XOM" : 0.106667,
        "SPY" : 0.095556,
        "QQQ" : 0.128889,
        "VXUS" : 0.095556
      },
      "utility" : 0.15030719259136505,
      "delta" : 9.483781989580442E-4
    }, {
      "symbol" : "SPY",
      "weights" : {
        "USO" : 0.095556,
        "GLD" : 0.095556,
        "MUB" : 0.095556,
        "VCLT" : 0.095556,
        "LQD" : 0.095556,
        "IGLB" : 0.095556,
        "XOM" : 0.095556,
        "SPY" : 0.106667,
        "QQQ" : 0.128889,
        "VXUS" : 0.095556
      },
      "utility" : 0.15003638650363132,
      "delta" : 6.775721112243227E-4
    }, {
      "symbol" : "QQQ",
      "weights" : {
        "USO" : 0.095556,
        "GLD" : 0.095556,
        "MUB" : 0.095556,
        "VCLT" : 0.095556,
        "LQD" : 0.095556,
        "IGLB" : 0.095556,
        "XOM" : 0.095556,
        "SPY" : 0.095556,
        "QQQ" : 0.14,
        "VXUS" : 0.095556
      },
      "utility" : 0.15096063190828568,
      "delta" : 0.0016018175158786785
    }, {
      "symbol" : "VXUS",
      "weights" : {
        "USO" : 0.095556,
        "GLD" : 0.095556,
        "MUB" : 0.095556,
        "VCLT" : 0.095556,
        "LQD" : 0.095556,
        "IGLB" : 0.095556,
        "XOM" : 0.095556,
        "SPY" : 0.095556,
        "QQQ" : 0.128889,
        "VXUS" : 0.106667
      },
      "utility" : 0.1491121371632481,
      "delta" : -2.4667722915891477E-4
    } ],
    "winner" : "QQQ",
    "endWeights" : {
      "USO" : 0.095556,
      "GLD" : 0.095556,
      "MUB" : 0.095556,
      "VCLT" : 0.095556,
      "LQD" : 0.095556,
      "IGLB" : 0.095556,
      "XOM" : 0.095556,
      "SPY" : 0.095556,
      "QQQ" : 0.14,
      "VXUS" : 0.095556
    },
    "endUtility" : 0.15096063190828568,
    "improvement" : 0.0016018175158786785
  }, {
    "epoch" : 4,
    "startWeights" : {
      "USO" : 0.095556,
      "GLD" : 0.095556,
      "MUB" : 0.095556,
      "VCLT" : 0.095556,
      "LQD" : 0.095556,
      "IGLB" : 0.095556,
      "XOM" : 0.095556,
      "SPY" : 0.095556,
      "QQQ" : 0.14,
      "VXUS" : 0.095556
    },
    "startUtility" : 0.15096063190828568,
    "feasibleCount" : 10,
    "variants" : [ {
      "symbol" : "USO",
      "weights" : {
        "USO" : 0.105556,
        "GLD" : 0.094444,
        "MUB" : 0.094444,
        "VCLT" : 0.094444,
        "LQD" : 0.094444,
        "IGLB" : 0.094444,
        "XOM" : 0.094444,
        "SPY" : 0.094444,
        "QQQ" : 0.138889,
        "VXUS" : 0.094444
      },
      "utility" : 0.15213789226846094,
      "delta" : 0.001177260360175264
    }, {
      "symbol" : "GLD",
      "weights" : {
        "USO" : 0.094444,
        "GLD" : 0.105556,
        "MUB" : 0.094444,
        "VCLT" : 0.094444,
        "LQD" : 0.094444,
        "IGLB" : 0.094444,
        "XOM" : 0.094444,
        "SPY" : 0.094444,
        "QQQ" : 0.138889,
        "VXUS" : 0.094444
      },
      "utility" : 0.1517871426327669,
      "delta" : 8.265107244812275E-4
    }, {
      "symbol" : "MUB",
      "weights" : {
        "USO" : 0.094444,
        "GLD" : 0.094444,
        "MUB" : 0.105556,
        "VCLT" : 0.094444,
        "LQD" : 0.094444,
        "IGLB" : 0.094444,
        "XOM" : 0.094444,
        "SPY" : 0.094444,
        "QQQ" : 0.138889,
        "VXUS" : 0.094444
      },
      "utility" : 0.14963091100124898,
      "delta" : -0.0013297209070367022
    }, {
      "symbol" : "VCLT",
      "weights" : {
        "USO" : 0.094444,
        "GLD" : 0.094444,
        "MUB" : 0.094444,
        "VCLT" : 0.105556,
        "LQD" : 0.094444,
        "IGLB" : 0.094444,
        "XOM" : 0.094444,
        "SPY" : 0.094444,
        "QQQ" : 0.138889,
        "VXUS" : 0.094444
      },
      "utility" : 0.14969559584655234,
      "delta" : -0.0012650360617333378
    }, {
      "symbol" : "LQD",
      "weights" : {
        "USO" : 0.094444,
        "GLD" : 0.094444,
        "MUB" : 0.094444,
        "VCLT" : 0.094444,
        "LQD" : 0.105556,
        "IGLB" : 0.094444,
        "XOM" : 0.094444,
        "SPY" : 0.094444,
        "QQQ" : 0.138889,
        "VXUS" : 0.094444
      },
      "utility" : 0.14971931230514818,
      "delta" : -0.001241319603137503
    }, {
      "symbol" : "IGLB",
      "weights" : {
        "USO" : 0.094444,
        "GLD" : 0.094444,
        "MUB" : 0.094444,
        "VCLT" : 0.094444,
        "LQD" : 0.094444,
        "IGLB" : 0.105556,
        "XOM" : 0.094444,
        "SPY" : 0.094444,
        "QQQ" : 0.138889,
        "VXUS" : 0.094444
      },
      "utility" : 0.14968441033335536,
      "delta" : -0.0012762215749303196
    }, {
      "symbol" : "XOM",
      "weights" : {
        "USO" : 0.094444,
        "GLD" : 0.094444,
        "MUB" : 0.094444,
        "VCLT" : 0.094444,
        "LQD" : 0.094444,
        "IGLB" : 0.094444,
        "XOM" : 0.105556,
        "SPY" : 0.094444,
        "QQQ" : 0.138889,
        "VXUS" : 0.094444
      },
      "utility" : 0.15191741222288171,
      "delta" : 9.567803145960341E-4
    }, {
      "symbol" : "SPY",
      "weights" : {
        "USO" : 0.094444,
        "GLD" : 0.094444,
        "MUB" : 0.094444,
        "VCLT" : 0.094444,
        "LQD" : 0.094444,
        "IGLB" : 0.094444,
        "XOM" : 0.094444,
        "SPY" : 0.105556,
        "QQQ" : 0.138889,
        "VXUS" : 0.094444
      },
      "utility" : 0.15161935681654679,
      "delta" : 6.587249082611046E-4
    }, {
      "symbol" : "QQQ",
      "weights" : {
        "USO" : 0.094444,
        "GLD" : 0.094444,
        "MUB" : 0.094444,
        "VCLT" : 0.094444,
        "LQD" : 0.094444,
        "IGLB" : 0.094444,
        "XOM" : 0.094444,
        "SPY" : 0.094444,
        "QQQ" : 0.15,
        "VXUS" : 0.094444
      },
      "utility" : 0.15252245294097994,
      "delta" : 0.001561821032694255
    }, {
      "symbol" : "VXUS",
      "weights" : {
        "USO" : 0.094444,
        "GLD" : 0.094444,
        "MUB" : 0.094444,
        "VCLT" : 0.094444,
        "LQD" : 0.094444,
        "IGLB" : 0.094444,
        "XOM" : 0.094444,
        "SPY" : 0.094444,
        "QQQ" : 0.138889,
        "VXUS" : 0.105556
      },
      "utility" : 0.15071164945074594,
      "delta" : -2.48982457539737E-4
    } ],
    "winner" : "QQQ",
    "endWeights" : {
      "USO" : 0.094444,
      "GLD" : 0.094444,
      "MUB" : 0.094444,
      "VCLT" : 0.094444,
      "LQD" : 0.094444,
      "IGLB" : 0.094444,
      "XOM" : 0.094444,
      "SPY" : 0.094444,
      "QQQ" : 0.15,
      "VXUS" : 0.094444
    },
    "endUtility" : 0.15252245294097994,
    "improvement" : 0.001561821032694255
  }, {
    "epoch" : 5,
    "startWeights" : {
      "USO" : 0.094444,
      "GLD" : 0.094444,
      "MUB" : 0.094444,
      "VCLT" : 0.094444,
      "LQD" : 0.094444,
      "IGLB" : 0.094444,
      "XOM" : 0.094444,
      "SPY" : 0.094444,
      "QQQ" : 0.15,
      "VXUS" : 0.094444
    },
    "startUtility" : 0.15252245294097994,
    "feasibleCount" : 10,
    "variants" : [ {
      "symbol" : "USO",
      "weights" : {
        "USO" : 0.104444,
        "GLD" : 0.093333,
        "MUB" : 0.093333,
        "VCLT" : 0.093333,
        "LQD" : 0.093333,
        "IGLB" : 0.093333,
        "XOM" : 0.093333,
        "SPY" : 0.093333,
        "QQQ" : 0.148889,
        "VXUS" : 0.093333
      },
      "utility" : 0.15372688471582827,
      "delta" : 0.0012044317748483302
    }, {
      "symbol" : "GLD",
      "weights" : {
        "USO" : 0.093333,
        "GLD" : 0.104444,
        "MUB" : 0.093333,
        "VCLT" : 0.093333,
        "LQD" : 0.093333,
        "IGLB" : 0.093333,
        "XOM" : 0.093333,
        "SPY" : 0.093333,
        "QQQ" : 0.148889,
        "VXUS" : 0.093333
      },
      "utility" : 0.153361052846492,
      "delta" : 8.385999055120774E-4
    }, {
      "symbol" : "MUB",
      "weights" : {
        "USO" : 0.093333,
        "GLD" : 0.093333,
        "MUB" : 0.104444,
        "VCLT" : 0.093333,
        "LQD" : 0.093333,
        "IGLB" : 0.093333,
        "XOM" : 0.093333,
        "SPY" : 0.093333,
        "QQQ" : 0.148889,
        "VXUS" : 0.093333
      },
      "utility" : 0.15118749946259663,
      "delta" : -0.001334953478383305
    }, {
      "symbol" : "VCLT",
      "weights" : {
        "USO" : 0.093333,
        "GLD" : 0.093333,
        "MUB" : 0.093333,
        "VCLT" : 0.104444,
        "LQD" : 0.093333,
        "IGLB" : 0.093333,
        "XOM" : 0.093333,
        "SPY" : 0.093333,
        "QQQ" : 0.148889,
        "VXUS" : 0.093333
      },
      "utility" : 0.15124642228710178,
      "delta" : -0.0012760306538781574
    }, {
      "symbol" : "LQD",
      "weights" : {
        "USO" : 0.093333,
        "GLD" : 0.093333,
        "MUB" : 0.093333,
        "VCLT" : 0.093333,
        "LQD" : 0.104444,
        "IGLB" : 0.093333,
        "XOM" : 0.093333,
        "SPY" : 0.093333,
        "QQQ" : 0.148889,
        "VXUS" : 0.093333
      },
      "utility" : 0.1512730987763735,
      "delta" : -0.0012493541646064477
    }, {
      "symbol" : "IGLB",
      "weights" : {
        "USO" : 0.093333,
        "GLD" : 0.093333,
        "MUB" : 0.093333,
        "VCLT" : 0.093333,
        "LQD" : 0.093333,
        "IGLB" : 0.104444,
        "XOM" : 0.093333,
        "SPY" : 0.093333,
        "QQQ" : 0.148889,
        "VXUS" : 0.093333
      },
      "utility" : 0.1512357427099263,
      "delta" : -0.001286710231053645
    }, {
      "symbol" : "XOM",
      "weights" : {
        "USO" : 0.093333,
        "GLD" : 0.093333,
        "MUB" : 0.093333,
        "VCLT" : 0.093333,
        "LQD" : 0.093333,
        "IGLB" : 0.093333,
        "XOM" : 0.104444,
        "SPY" : 0.093333,
        "QQQ" : 0.148889,
        "VXUS" : 0.093333
      },
      "utility" : 0.1535097655592466,
      "delta" : 9.87312618266678E-4
    }, {
      "symbol" : "SPY",
      "weights" : {
        "USO" : 0.093333,
        "GLD" : 0.093333,
        "MUB" : 0.093333,
        "VCLT" : 0.093333,
        "LQD" : 0.093333,
        "IGLB" : 0.093333,
        "XOM" : 0.093333,
        "SPY" : 0.104444,
        "QQQ" : 0.148889,
        "VXUS" : 0.093333
      },
      "utility" : 0.15315046048447228,
      "delta" : 6.280075434923482E-4
    }, {
      "symbol" : "QQQ",
      "weights" : {
        "USO" : 0.093333,
        "GLD" : 0.093333,
        "MUB" : 0.093333,
        "VCLT" : 0.093333,
        "LQD" : 0.093333,
        "IGLB" : 0.093333,
        "XOM" : 0.093333,
        "SPY" : 0.093333,
        "QQQ" : 0.16,
        "VXUS" : 0.093333
      },
      "utility" : 0.1540302830661996,
      "delta" : 0.0015078301252196558
    }, {
      "symbol" : "VXUS",
      "weights" : {
        "USO" : 0.093333,
        "GLD" : 0.093333,
        "MUB" : 0.093333,
        "VCLT" : 0.093333,
        "LQD" : 0.093333,
        "IGLB" : 0.093333,
        "XOM" : 0.093333,
        "SPY" : 0.093333,
        "QQQ" : 0.148889,
        "VXUS" : 0.104444
      },
      "utility" : 0.15226478780386843,
      "delta" : -2.5766513711150685E-4
    } ],
    "winner" : "QQQ",
    "endWeights" : {
      "USO" : 0.093333,
      "GLD" : 0.093333,
      "MUB" : 0.093333,
      "VCLT" : 0.093333,
      "LQD" : 0.093333,
      "IGLB" : 0.093333,
      "XOM" : 0.093333,
      "SPY" : 0.093333,
      "QQQ" : 0.16,
      "VXUS" : 0.093333
    },
    "endUtility" : 0.1540302830661996,
    "improvement" : 0.0015078301252196558
  }, {
    "epoch" : 6,
    "startWeights" : {
      "USO" : 0.093333,
      "GLD" : 0.093333,
      "MUB" : 0.093333,
      "VCLT" : 0.093333,
      "LQD" : 0.093333,
      "IGLB" : 0.093333,
      "XOM" : 0.093333,
      "SPY" : 0.093333,
      "QQQ" : 0.16,
      "VXUS" : 0.093333
    },
    "startUtility" : 0.1540302830661996,
    "feasibleCount" : 10,
    "variants" : [ {
      "symbol" : "USO",
      "weights" : {
        "USO" : 0.103333,
        "GLD" : 0.092222,
        "MUB" : 0.092222,
        "VCLT" : 0.092222,
        "LQD" : 0.092222,
        "IGLB" : 0.092222,
        "XOM" : 0.092222,
        "SPY" : 0.092222,
        "QQQ" : 0.158889,
        "VXUS" : 0.092222
      },
      "utility" : 0.15528547300384046,
      "delta" : 0.0012551899376408715
    }, {
      "symbol" : "GLD",
      "weights" : {
        "USO" : 0.092222,
        "GLD" : 0.103333,
        "MUB" : 0.092222,
        "VCLT" : 0.092222,
        "LQD" : 0.092222,
        "IGLB" : 0.092222,
        "XOM" : 0.092222,
        "SPY" : 0.092222,
        "QQQ" : 0.158889,
        "VXUS" : 0.092222
      },
      "utility" : 0.1548966500828027,
      "delta" : 8.663670166031145E-4
    }, {
      "symbol" : "MUB",
      "weights" : {
        "USO" : 0.092222,
        "GLD" : 0.092222,
        "MUB" : 0.103333,
        "VCLT" : 0.092222,
        "LQD" : 0.092222,
        "IGLB" : 0.092222,
        "XOM" : 0.092222,
        "SPY" : 0.092222,
        "QQQ" : 0.158889,
        "VXUS" : 0.092222
      },
      "utility" : 0.1526983318699917,
      "delta" : -0.0013319511962078812
    }, {
      "symbol" : "VCLT",
      "weights" : {
        "USO" : 0.092222,
        "GLD" : 0.092222,
        "MUB" : 0.092222,
        "VCLT" : 0.103333,
        "LQD" : 0.092222,
        "IGLB" : 0.092222,
        "XOM" : 0.092222,
        "SPY" : 0.092222,
        "QQQ" : 0.158889,
        "VXUS" : 0.092222
      },
      "utility" : 0.15276770672865225,
      "delta" : -0.0012625763375473387
    }, {
      "symbol" : "LQD",
      "weights" : {
        "USO" : 0.092222,
        "GLD" : 0.092222,
        "MUB" : 0.092222,
        "VCLT" : 0.092222,
        "LQD" : 0.103333,
        "IGLB" : 0.092222,
        "XOM" : 0.092222,
        "SPY" : 0.092222,
        "QQQ" : 0.158889,
        "VXUS" : 0.092222
      },
      "utility" : 0.1527902067126938,
      "delta" : -0.0012400763535057868
    }, {
      "symbol" : "IGLB",
      "weights" : {
        "USO" : 0.092222,
        "GLD" : 0.092222,
        "MUB" : 0.092222,
        "VCLT" : 0.092222,
        "LQD" : 0.092222,
        "IGLB" : 0.103333,
        "XOM" : 0.092222,
        "SPY" : 0.092222,
        "QQQ" : 0.158889,
        "VXUS" : 0.092222
      },
      "utility" : 0.1527571358417261,
      "delta" : -0.0012731472244734976
    }, {
      "symbol" : "XOM",
      "weights" : {
        "USO" : 0.092222,
        "GLD" : 0.092222,
        "MUB" : 0.092222,
        "VCLT" : 0.092222,
        "LQD" : 0.092222,
        "IGLB" : 0.092222,
        "XOM" : 0.103333,
        "SPY" : 0.092222,
        "QQQ" : 0.158889,
        "VXUS" : 0.092222
      },
      "utility" : 0.1550788132310479,
      "delta" : 0.0010485301648483214
    }, {
      "symbol" : "SPY",
      "weights" : {
        "USO" : 0.092222,
        "GLD" : 0.092222,
        "MUB" : 0.092222,
        "VCLT" : 0.092222,
        "LQD" : 0.092222,
        "IGLB" : 0.092222,
        "XOM" : 0.092222,
        "SPY" : 0.103333,
        "QQQ" : 0.158889,
        "VXUS" : 0.092222
      },
      "utility" : 0.15465280582302932,
      "delta" : 6.225227568297242E-4
    }, {
      "symbol" : "QQQ",
      "weights" : {
        "USO" : 0.092222,
        "GLD" : 0.092222,
        "MUB" : 0.092222,
        "VCLT" : 0.092222,
        "LQD" : 0.092222,
        "IGLB" : 0.092222,
        "XOM" : 0.092222,
        "SPY" : 0.092222,
        "QQQ" : 0.17,
        "VXUS" : 0.092222
      },
      "utility" : 0.15553877091271873,
      "delta" : 0.0015084878465191354
    }, {
      "symbol" : "VXUS",
      "weights" : {
        "USO" : 0.092222,
        "GLD" : 0.092222,
        "MUB" : 0.092222,
        "VCLT" : 0.092222,
        "LQD" : 0.092222,
        "IGLB" : 0.092222,
        "XOM" : 0.092222,
        "SPY" : 0.092222,
        "QQQ" : 0.158889,
        "VXUS" : 0.103333
      },
      "utility" : 0.15379373208827643,
      "delta" : -2.3655097792316115E-4
    } ],
    "winner" : "QQQ",
    "endWeights" : {
      "USO" : 0.092222,
      "GLD" : 0.092222,
      "MUB" : 0.092222,
      "VCLT" : 0.092222,
      "LQD" : 0.092222,
      "IGLB" : 0.092222,
      "XOM" : 0.092222,
      "SPY" : 0.092222,
      "QQQ" : 0.17,
      "VXUS" : 0.092222
    },
    "endUtility" : 0.15553877091271873,
    "improvement" : 0.0015084878465191354
  }, {
    "epoch" : 7,
    "startWeights" : {
      "USO" : 0.092222,
      "GLD" : 0.092222,
      "MUB" : 0.092222,
      "VCLT" : 0.092222,
      "LQD" : 0.092222,
      "IGLB" : 0.092222,
      "XOM" : 0.092222,
      "SPY" : 0.092222,
      "QQQ" : 0.17,
      "VXUS" : 0.092222
    },
    "startUtility" : 0.15553877091271873,
    "feasibleCount" : 10,
    "variants" : [ {
      "symbol" : "USO",
      "weights" : {
        "USO" : 0.102222,
        "GLD" : 0.091111,
        "MUB" : 0.091111,
        "VCLT" : 0.091111,
        "LQD" : 0.091111,
        "IGLB" : 0.091111,
        "XOM" : 0.091111,
        "SPY" : 0.091111,
        "QQQ" : 0.168889,
        "VXUS" : 0.091111
      },
      "utility" : 0.15681156218898537,
      "delta" : 0.0012727912762666438
    }, {
      "symbol" : "GLD",
      "weights" : {
        "USO" : 0.091111,
        "GLD" : 0.102222,
        "MUB" : 0.091111,
        "VCLT" : 0.091111,
        "LQD" : 0.091111,
        "IGLB" : 0.091111,
        "XOM" : 0.091111,
        "SPY" : 0.091111,
        "QQQ" : 0.168889,
        "VXUS" : 0.091111
      },
      "utility" : 0.1564201232663207,
      "delta" : 8.813523536019829E-4
    }, {
      "symbol" : "MUB",
      "weights" : {
        "USO" : 0.091111,
        "GLD" : 0.091111,
        "MUB" : 0.102222,
        "VCLT" : 0.091111,
        "LQD" : 0.091111,
        "IGLB" : 0.091111,
        "XOM" : 0.091111,
        "SPY" : 0.091111,
        "QQQ" : 0.168889,
        "VXUS" : 0.091111
      },
      "utility" : 0.15420817283382646,
      "delta" : -0.00133059807889227
    }, {
      "symbol" : "VCLT",
      "weights" : {
        "USO" : 0.091111,
        "GLD" : 0.091111,
        "MUB" : 0.091111,
        "VCLT" : 0.102222,
        "LQD" : 0.091111,
        "IGLB" : 0.091111,
        "XOM" : 0.091111,
        "SPY" : 0.091111,
        "QQQ" : 0.168889,
        "VXUS" : 0.091111
      },
      "utility" : 0.15427384763006705,
      "delta" : -0.001264923282651681
    }, {
      "symbol" : "LQD",
      "weights" : {
        "USO" : 0.091111,
        "GLD" : 0.091111,
        "MUB" : 0.091111,
        "VCLT" : 0.091111,
        "LQD" : 0.102222,
        "IGLB" : 0.091111,
        "XOM" : 0.091111,
        "SPY" : 0.091111,
        "QQQ" : 0.168889,
        "VXUS" : 0.091111
      },
      "utility" : 0.1542984168863407,
      "delta" : -0.0012403540263780377
    }, {
      "symbol" : "IGLB",
      "weights" : {
        "USO" : 0.091111,
        "GLD" : 0.091111,
        "MUB" : 0.091111,
        "VCLT" : 0.091111,
        "LQD" : 0.091111,
        "IGLB" : 0.102222,
        "XOM" : 0.091111,
        "SPY" : 0.091111,
        "QQQ" : 0.168889,
        "VXUS" : 0.091111
      },
      "utility" : 0.1542627968113036,
      "delta" : -0.0012759741014151393
    }, {
      "symbol" : "XOM",
      "weights" : {
        "USO" : 0.091111,
        "GLD" : 0.091111,
        "MUB" : 0.091111,
        "VCLT" : 0.091111,
        "LQD" : 0.091111,
        "IGLB" : 0.091111,
        "XOM" : 0.102222,
        "SPY" : 0.091111,
        "QQQ" : 0.168889,
        "VXUS" : 0.091111
      },
      "utility" : 0.15660220616425052,
      "delta" : 0.0010634352515317969
    }, {
      "symbol" : "SPY",
      "weights" : {
        "USO" : 0.091111,
        "GLD" : 0.091111,
        "MUB" : 0.091111,
        "VCLT" : 0.091111,
        "LQD" : 0.091111,
        "IGLB" : 0.091111,
        "XOM" : 0.091111,
        "SPY" : 0.102222,
        "QQQ" : 0.168889,
        "VXUS" : 0.091111
      },
      "utility" : 0.15614135371110685,
      "delta" : 6.025827983881238E-4
    }, {
      "symbol" : "QQQ",
      "weights" : {
        "USO" : 0.091111,
        "GLD" : 0.091111,
        "MUB" : 0.091111,
        "VCLT" : 0.091111,
        "LQD" : 0.091111,
        "IGLB" : 0.091111,
        "XOM" : 0.091111,
        "SPY" : 0.091111,
        "QQQ" : 0.18,
        "VXUS" : 0.091111
      },
      "utility" : 0.15701278142458985,
      "delta" : 0.0014740105118711266
    }, {
      "symbol" : "VXUS",
      "weights" : {
        "USO" : 0.091111,
        "GLD" : 0.091111,
        "MUB" : 0.091111,
        "VCLT" : 0.091111,
        "LQD" : 0.091111,
        "IGLB" : 0.091111,
        "XOM" : 0.091111,
        "SPY" : 0.091111,
        "QQQ" : 0.168889,
        "VXUS" : 0.102222
      },
      "utility" : 0.15528832847576135,
      "delta" : -2.5044243695737656E-4
    } ],
    "winner" : "QQQ",
    "endWeights" : {
      "USO" : 0.091111,
      "GLD" : 0.091111,
      "MUB" : 0.091111,
      "VCLT" : 0.091111,
      "LQD" : 0.091111,
      "IGLB" : 0.091111,
      "XOM" : 0.091111,
      "SPY" : 0.091111,
      "QQQ" : 0.18,
      "VXUS" : 0.091111
    },
    "endUtility" : 0.15701278142458985,
    "improvement" : 0.0014740105118711266
  }, {
    "epoch" : 8,
    "startWeights" : {
      "USO" : 0.091111,
      "GLD" : 0.091111,
      "MUB" : 0.091111,
      "VCLT" : 0.091111,
      "LQD" : 0.091111,
      "IGLB" : 0.091111,
      "XOM" : 0.091111,
      "SPY" : 0.091111,
      "QQQ" : 0.18,
      "VXUS" : 0.091111
    },
    "startUtility" : 0.15701278142458985,
    "feasibleCount" : 10,
    "variants" : [ {
      "symbol" : "USO",
      "weights" : {
        "USO" : 0.101111,
        "GLD" : 0.09,
        "MUB" : 0.09,
        "VCLT" : 0.09,
        "LQD" : 0.09,
        "IGLB" : 0.09,
        "XOM" : 0.09,
        "SPY" : 0.09,
        "QQQ" : 0.178889,
        "VXUS" : 0.09
      },
      "utility" : 0.15831612564126396,
      "delta" : 0.0013033442166741072
    }, {
      "symbol" : "GLD",
      "weights" : {
        "USO" : 0.09,
        "GLD" : 0.101111,
        "MUB" : 0.09,
        "VCLT" : 0.09,
        "LQD" : 0.09,
        "IGLB" : 0.09,
        "XOM" : 0.09,
        "SPY" : 0.09,
        "QQQ" : 0.178889,
        "VXUS" : 0.09
      },
      "utility" : 0.15788731657584645,
      "delta" : 8.745351512566002E-4
    }, {
      "symbol" : "MUB",
      "weights" : {
        "USO" : 0.09,
        "GLD" : 0.09,
        "MUB" : 0.101111,
        "VCLT" : 0.09,
        "LQD" : 0.09,
        "IGLB" : 0.09,
        "XOM" : 0.09,
        "SPY" : 0.09,
        "QQQ" : 0.178889,
        "VXUS" : 0.09
      },
      "utility" : 0.15568076223747307,
      "delta" : -0.0013320191871167841
    }, {
      "symbol" : "VCLT",
      "weights" : {
        "USO" : 0.09,
        "GLD" : 0.09,
        "MUB" : 0.09,
        "VCLT" : 0.101111,
        "LQD" : 0.09,
        "IGLB" : 0.09,
        "XOM" : 0.09,
        "SPY" : 0.09,
        "QQQ" : 0.178889,
        "VXUS" : 0.09
      },
      "utility" : 0.15575046408610668,
      "delta" : -0.001262317338483171
    }, {
      "symbol" : "LQD",
      "weights" : {
        "USO" : 0.09,
        "GLD" : 0.09,
        "MUB" : 0.09,
        "VCLT" : 0.09,
        "LQD" : 0.101111,
        "IGLB" : 0.09,
        "XOM" : 0.09,
        "SPY" : 0.09,
        "QQQ" : 0.178889,
        "VXUS" : 0.09
      },
      "utility" : 0.15577269887795311,
      "delta" : -0.0012400825466367393
    }, {
      "symbol" : "IGLB",
      "weights" : {
        "USO" : 0.09,
        "GLD" : 0.09,
        "MUB" : 0.09,
        "VCLT" : 0.09,
        "LQD" : 0.09,
        "IGLB" : 0.101111,
        "XOM" : 0.09,
        "SPY" : 0.09,
        "QQQ" : 0.178889,
        "VXUS" : 0.09
      },
      "utility" : 0.15573875154886793,
      "delta" : -0.0012740298757219215
    }, {
      "symbol" : "XOM",
      "weights" : {
        "USO" : 0.09,
        "GLD" : 0.09,
        "MUB" : 0.09,
        "VCLT" : 0.09,
        "LQD" : 0.09,
        "IGLB" : 0.09,
        "XOM" : 0.101111,
        "SPY" : 0.09,
        "QQQ" : 0.178889,
        "VXUS" : 0.09
      },
      "utility" : 0.1581085368304446,
      "delta" : 0.0010957554058547425
    }, {
      "symbol" : "SPY",
      "weights" : {
        "USO" : 0.09,
        "GLD" : 0.09,
        "MUB" : 0.09,
        "VCLT" : 0.09,
        "LQD" : 0.09,
        "IGLB" : 0.09,
        "XOM" : 0.09,
        "SPY" : 0.101111,
        "QQQ" : 0.178889,
        "VXUS" : 0.09
      },
      "utility" : 0.1575894611225015,
      "delta" : 5.766796979116418E-4
    }, {
      "symbol" : "QQQ",
      "weights" : {
        "USO" : 0.09,
        "GLD" : 0.09,
        "MUB" : 0.09,
        "VCLT" : 0.09,
        "LQD" : 0.09,
        "IGLB" : 0.09,
        "XOM" : 0.09,
        "SPY" : 0.09,
        "QQQ" : 0.19,
        "VXUS" : 0.09
      },
      "utility" : 0.1584297580350422,
      "delta" : 0.0014169766104523418
    }, {
      "symbol" : "VXUS",
      "weights" : {
        "USO" : 0.09,
        "GLD" : 0.09,
        "MUB" : 0.09,
        "VCLT" : 0.09,
        "LQD" : 0.09,
        "IGLB" : 0.09,
        "XOM" : 0.09,
        "SPY" : 0.09,
        "QQQ" : 0.178889,
        "VXUS" : 0.101111
      },
      "utility" : 0.1567485456553572,
      "delta" : -2.6423576923265135E-4
    } ],
    "winner" : "QQQ",
    "endWeights" : {
      "USO" : 0.09,
      "GLD" : 0.09,
      "MUB" : 0.09,
      "VCLT" : 0.09,
      "LQD" : 0.09,
      "IGLB" : 0.09,
      "XOM" : 0.09,
      "SPY" : 0.09,
      "QQQ" : 0.19,
      "VXUS" : 0.09
    },
    "endUtility" : 0.1584297580350422,
    "improvement" : 0.0014169766104523418
  }, {
    "epoch" : 9,
    "startWeights" : {
      "USO" : 0.09,
      "GLD" : 0.09,
      "MUB" : 0.09,
      "VCLT" : 0.09,
      "LQD" : 0.09,
      "IGLB" : 0.09,
      "XOM" : 0.09,
      "SPY" : 0.09,
      "QQQ" : 0.19,
      "VXUS" : 0.09
    },
    "startUtility" : 0.1584297580350422,
    "feasibleCount" : 10,
    "variants" : [ {
      "symbol" : "USO",
      "weights" : {
        "USO" : 0.1,
        "GLD" : 0.088889,
        "MUB" : 0.088889,
        "VCLT" : 0.088889,
        "LQD" : 0.088889,
        "IGLB" : 0.088889,
        "XOM" : 0.088889,
        "SPY" : 0.088889,
        "QQQ" : 0.188889,
        "VXUS" : 0.088889
      },
      "utility" : 0.15977544607111224,
      "delta" : 0.0013456880360700474
    }, {
      "symbol" : "GLD",
      "weights" : {
        "USO" : 0.088889,
        "GLD" : 0.1,
        "MUB" : 0.088889,
        "VCLT" : 0.088889,
        "LQD" : 0.088889,
        "IGLB" : 0.088889,
        "XOM" : 0.088889,
        "SPY" : 0.088889,
        "QQQ" : 0.188889,
        "VXUS" : 0.088889
      },
      "utility" : 0.1592916410498845,
      "delta" : 8.618830148423018E-4
    }, {
      "symbol" : "MUB",
      "weights" : {
        "USO" : 0.088889,
        "GLD" : 0.088889,
        "MUB" : 0.1,
        "VCLT" : 0.088889,
        "LQD" : 0.088889,
        "IGLB" : 0.088889,
        "XOM" : 0.088889,
        "SPY" : 0.088889,
        "QQQ" : 0.188889,
        "VXUS" : 0.088889
      },
      "utility" : 0.1570909297705947,
      "delta" : -0.0013388282644475058
    }, {
      "symbol" : "VCLT",
      "weights" : {
        "USO" : 0.088889,
        "GLD" : 0.088889,
        "MUB" : 0.088889,
        "VCLT" : 0.1,
        "LQD" : 0.088889,
        "IGLB" : 0.088889,
        "XOM" : 0.088889,
        "SPY" : 0.088889,
        "QQQ" : 0.188889,
        "VXUS" : 0.088889
      },
      "utility" : 0.15715606598045062,
      "delta" : -0.0012736920545915742
    }, {
      "symbol" : "LQD",
      "weights" : {
        "USO" : 0.088889,
        "GLD" : 0.088889,
        "MUB" : 0.088889,
        "VCLT" : 0.088889,
        "LQD" : 0.1,
        "IGLB" : 0.088889,
        "XOM" : 0.088889,
        "SPY" : 0.088889,
        "QQQ" : 0.188889,
        "VXUS" : 0.088889
      },
      "utility" : 0.15717621458447217,
      "delta" : -0.0012535434505700216
    }, {
      "symbol" : "IGLB",
      "weights" : {
        "USO" : 0.088889,
        "GLD" : 0.088889,
        "MUB" : 0.088889,
        "VCLT" : 0.088889,
        "LQD" : 0.088889,
        "IGLB" : 0.1,
        "XOM" : 0.088889,
        "SPY" : 0.088889,
        "QQQ" : 0.188889,
        "VXUS" : 0.088889
      },
      "utility" : 0.15714548026982414,
      "delta" : -0.001284277765218056
    }, {
      "symbol" : "XOM",
      "weights" : {
        "USO" : 0.088889,
        "GLD" : 0.088889,
        "MUB" : 0.088889,
        "VCLT" : 0.088889,
        "LQD" : 0.088889,
        "IGLB" : 0.088889,
        "XOM" : 0.1,
        "SPY" : 0.088889,
        "QQQ" : 0.188889,
        "VXUS" : 0.088889
      },
      "utility" : 0.15958872776241576,
      "delta" : 0.00115896972737356
    }, {
      "symbol" : "SPY",
      "weights" : {
        "USO" : 0.088889,
        "GLD" : 0.088889,
        "MUB" : 0.088889,
        "VCLT" : 0.088889,
        "LQD" : 0.088889,
        "IGLB" : 0.088889,
        "XOM" : 0.088889,
        "SPY" : 0.1,
        "QQQ" : 0.188889,
        "VXUS" : 0.088889
      },
      "utility" : 0.15897790067125456,
      "delta" : 5.48142636212362E-4
    }, {
      "symbol" : "QQQ",
      "weights" : {
        "USO" : 0.088889,
        "GLD" : 0.088889,
        "MUB" : 0.088889,
        "VCLT" : 0.088889,
        "LQD" : 0.088889,
        "IGLB" : 0.088889,
        "XOM" : 0.088889,
        "SPY" : 0.088889,
        "QQQ" : 0.2,
        "VXUS" : 0.088889
      },
      "utility" : 0.15980143494220492,
      "delta" : 0.0013716769071627222
    }, {
      "symbol" : "VXUS",
      "weights" : {
        "USO" : 0.088889,
        "GLD" : 0.088889,
        "MUB" : 0.088889,
        "VCLT" : 0.088889,
        "LQD" : 0.088889,
        "IGLB" : 0.088889,
        "XOM" : 0.088889,
        "SPY" : 0.088889,
        "QQQ" : 0.188889,
        "VXUS" : 0.1
      },
      "utility" : 0.15814700821128938,
      "delta" : -2.8274982375281477E-4
    } ],
    "winner" : "QQQ",
    "endWeights" : {
      "USO" : 0.088889,
      "GLD" : 0.088889,
      "MUB" : 0.088889,
      "VCLT" : 0.088889,
      "LQD" : 0.088889,
      "IGLB" : 0.088889,
      "XOM" : 0.088889,
      "SPY" : 0.088889,
      "QQQ" : 0.2,
      "VXUS" : 0.088889
    },
    "endUtility" : 0.15980143494220492,
    "improvement" : 0.0013716769071627222
  }, {
    "epoch" : 10,
    "startWeights" : {
      "USO" : 0.088889,
      "GLD" : 0.088889,
      "MUB" : 0.088889,
      "VCLT" : 0.088889,
      "LQD" : 0.088889,
      "IGLB" : 0.088889,
      "XOM" : 0.088889,
      "SPY" : 0.088889,
      "QQQ" : 0.2,
      "VXUS" : 0.088889
    },
    "startUtility" : 0.15980143494220492,
    "feasibleCount" : 10,
    "variants" : [ {
      "symbol" : "USO",
      "weights" : {
        "USO" : 0.098889,
        "GLD" : 0.087778,
        "MUB" : 0.087778,
        "VCLT" : 0.087778,
        "LQD" : 0.087778,
        "IGLB" : 0.087778,
        "XOM" : 0.087778,
        "SPY" : 0.087778,
        "QQQ" : 0.198889,
        "VXUS" : 0.087778
      },
      "utility" : 0.16120485699501821,
      "delta" : 0.0014034220528132968
    }, {
      "symbol" : "GLD",
      "weights" : {
        "USO" : 0.087778,
        "GLD" : 0.098889,
        "MUB" : 0.087778,
        "VCLT" : 0.087778,
        "LQD" : 0.087778,
        "IGLB" : 0.087778,
        "XOM" : 0.087778,
        "SPY" : 0.087778,
        "QQQ" : 0.198889,
        "VXUS" : 0.087778
      },
      "utility" : 0.16065948383385664,
      "delta" : 8.580488916517248E-4
    }, {
      "symbol" : "MUB",
      "weights" : {
        "USO" : 0.087778,
        "GLD" : 0.087778,
        "MUB" : 0.098889,
        "VCLT" : 0.087778,
        "LQD" : 0.087778,
        "IGLB" : 0.087778,
        "XOM" : 0.087778,
        "SPY" : 0.087778,
        "QQQ" : 0.198889,
        "VXUS" : 0.087778
      },
      "utility" : 0.15845874200762308,
      "delta" : -0.001342692934581835
    }, {
      "symbol" : "VCLT",
      "weights" : {
        "USO" : 0.087778,
        "GLD" : 0.087778,
        "MUB" : 0.087778,
        "VCLT" : 0.098889,
        "LQD" : 0.087778,
        "IGLB" : 0.087778,
        "XOM" : 0.087778,
        "SPY" : 0.087778,
        "QQQ" : 0.198889,
        "VXUS" : 0.087778
      },
      "utility" : 0.15852150843176577,
      "delta" : -0.00127992651043915
    }, {
      "symbol" : "LQD",
      "weights" : {
        "USO" : 0.087778,
        "GLD" : 0.087778,
        "MUB" : 0.087778,
        "VCLT" : 0.087778,
        "LQD" : 0.098889,
        "IGLB" : 0.087778,
        "XOM" : 0.087778,
        "SPY" : 0.087778,
        "QQQ" : 0.198889,
        "VXUS" : 0.087778
      },
      "utility" : 0.15854462728256125,
      "delta" : -0.0012568076596436717
    }, {
      "symbol" : "IGLB",
      "weights" : {
        "USO" : 0.087778,
        "GLD" : 0.087778,
        "MUB" : 0.087778,
        "VCLT" : 0.087778,
        "LQD" : 0.087778,
        "IGLB" : 0.098889,
        "XOM" : 0.087778,
        "SPY" : 0.087778,
        "QQQ" : 0.198889,
        "VXUS" : 0.087778
      },
      "utility" : 0.1585117305814542,
      "delta" : -0.0012897043607507097
    }, {
      "symbol" : "XOM",
      "weights" : {
        "USO" : 0.087778,
        "GLD" : 0.087778,
        "MUB" : 0.087778,
        "VCLT" : 0.087778,
        "LQD" : 0.087778,
        "IGLB" : 0.087778,
        "XOM" : 0.098889,
        "SPY" : 0.087778,
        "QQQ" : 0.198889,
        "VXUS" : 0.087778
      },
      "utility" : 0.16101467706513306,
      "delta" : 0.0012132421229281432
    }, {
      "symbol" : "SPY",
      "weights" : {
        "USO" : 0.087778,
        "GLD" : 0.087778,
        "MUB" : 0.087778,
        "VCLT" : 0.087778,
        "LQD" : 0.087778,
        "IGLB" : 0.087778,
        "XOM" : 0.087778,
        "SPY" : 0.098889,
        "QQQ" : 0.198889,
        "VXUS" : 0.087778
      },
      "utility" : 0.16034251202364158,
      "delta" : 5.410770814366639E-4
    }, {
      "symbol" : "QQQ",
      "weights" : {
        "USO" : 0.087778,
        "GLD" : 0.087778,
        "MUB" : 0.087778,
        "VCLT" : 0.087778,
        "LQD" : 0.087778,
        "IGLB" : 0.087778,
        "XOM" : 0.087778,
        "SPY" : 0.087778,
        "QQQ" : 0.21,
        "VXUS" : 0.087778
      },
      "utility" : 0.16114631776743432,
      "delta" : 0.0013448828252294043
    }, {
      "symbol" : "VXUS",
      "weights" : {
        "USO" : 0.087778,
        "GLD" : 0.087778,
        "MUB" : 0.087778,
        "VCLT" : 0.087778,
        "LQD" : 0.087778,
        "IGLB" : 0.087778,
        "XOM" : 0.087778,
        "SPY" : 0.087778,
        "QQQ" : 0.198889,
        "VXUS" : 0.098889
      },
      "utility" : 0.15951860904158138,
      "delta" : -2.828259006235345E-4
    } ],
    "winner" : "USO",
    "endWeights" : {
      "USO" : 0.098889,
      "GLD" : 0.087778,
      "MUB" : 0.087778,
      "VCLT" : 0.087778,
      "LQD" : 0.087778,
      "IGLB" : 0.087778,
      "XOM" : 0.087778,
      "SPY" : 0.087778,
      "QQQ" : 0.198889,
      "VXUS" : 0.087778
    },
    "endUtility" : 0.16120485699501821,
    "improvement" : 0.0014034220528132968
  }, {
    "epoch" : 11,
    "startWeights" : {
      "USO" : 0.098889,
      "GLD" : 0.087778,
      "MUB" : 0.087778,
      "VCLT" : 0.087778,
      "LQD" : 0.087778,
      "IGLB" : 0.087778,
      "XOM" : 0.087778,
      "SPY" : 0.087778,
      "QQQ" : 0.198889,
      "VXUS" : 0.087778
    },
    "startUtility" : 0.16120485699501821,
    "feasibleCount" : 10,
    "variants" : [ {
      "symbol" : "USO",
      "weights" : {
        "USO" : 0.108889,
        "GLD" : 0.086667,
        "MUB" : 0.086667,
        "VCLT" : 0.086667,
        "LQD" : 0.086667,
        "IGLB" : 0.086667,
        "XOM" : 0.086667,
        "SPY" : 0.086667,
        "QQQ" : 0.197778,
        "VXUS" : 0.086667
      },
      "utility" : 0.16247466712604486,
      "delta" : 0.001269810131026644
    }, {
      "symbol" : "GLD",
      "weights" : {
        "USO" : 0.097778,
        "GLD" : 0.097778,
        "MUB" : 0.086667,
        "VCLT" : 0.086667,
        "LQD" : 0.086667,
        "IGLB" : 0.086667,
        "XOM" : 0.086667,
        "SPY" : 0.086667,
        "QQQ" : 0.197778,
        "VXUS" : 0.086667
      },
      "utility" : 0.16207075403681376,
      "delta" : 8.658970417955436E-4
    }, {
      "symbol" : "MUB",
      "weights" : {
        "USO" : 0.097778,
        "GLD" : 0.086667,
        "MUB" : 0.097778,
        "VCLT" : 0.086667,
        "LQD" : 0.086667,
        "IGLB" : 0.086667,
        "XOM" : 0.086667,
        "SPY" : 0.086667,
        "QQQ" : 0.197778,
        "VXUS" : 0.086667
      },
      "utility" : 0.15987223352502108,
      "delta" : -0.0013326234699971296
    }, {
      "symbol" : "VCLT",
      "weights" : {
        "USO" : 0.097778,
        "GLD" : 0.086667,
        "MUB" : 0.086667,
        "VCLT" : 0.097778,
        "LQD" : 0.086667,
        "IGLB" : 0.086667,
        "XOM" : 0.086667,
        "SPY" : 0.086667,
        "QQQ" : 0.197778,
        "VXUS" : 0.086667
      },
      "utility" : 0.1599462065397597,
      "delta" : -0.0012586504552585254
    }, {
      "symbol" : "LQD",
      "weights" : {
        "USO" : 0.097778,
        "GLD" : 0.086667,
        "MUB" : 0.086667,
        "VCLT" : 0.086667,
        "LQD" : 0.097778,
        "IGLB" : 0.086667,
        "XOM" : 0.086667,
        "SPY" : 0.086667,
        "QQQ" : 0.197778,
        "VXUS" : 0.086667
      },
      "utility" : 0.15996641525971989,
      "delta" : -0.001238441735298329
    }, {
      "symbol" : "IGLB",
      "weights" : {
        "USO" : 0.097778,
        "GLD" : 0.086667,
        "MUB" : 0.086667,
        "VCLT" : 0.086667,
        "LQD" : 0.086667,
        "IGLB" : 0.097778,
        "XOM" : 0.086667,
        "SPY" : 0.086667,
        "QQQ" : 0.197778,
        "VXUS" : 0.086667
      },
      "utility" : 0.159935356266411,
      "delta" : -0.001269500728607209
    }, {
      "symbol" : "XOM",
      "weights" : {
        "USO" : 0.097778,
        "GLD" : 0.086667,
        "MUB" : 0.086667,
        "VCLT" : 0.086667,
        "LQD" : 0.086667,
        "IGLB" : 0.086667,
        "XOM" : 0.097778,
        "SPY" : 0.086667,
        "QQQ" : 0.197778,
        "VXUS" : 0.086667
      },
      "utility" : 0.1623198604560778,
      "delta" : 0.0011150034610595827
    }, {
      "symbol" : "SPY",
      "weights" : {
        "USO" : 0.097778,
        "GLD" : 0.086667,
        "MUB" : 0.086667,
        "VCLT" : 0.086667,
        "LQD" : 0.086667,
        "IGLB" : 0.086667,
        "XOM" : 0.086667,
        "SPY" : 0.097778,
        "QQQ" : 0.197778,
        "VXUS" : 0.086667
      },
      "utility" : 0.16176939793421952,
      "delta" : 5.645409392013023E-4
    }, {
      "symbol" : "QQQ",
      "weights" : {
        "USO" : 0.097778,
        "GLD" : 0.086667,
        "MUB" : 0.086667,
        "VCLT" : 0.086667,
        "LQD" : 0.086667,
        "IGLB" : 0.086667,
        "XOM" : 0.086667,
        "SPY" : 0.086667,
        "QQQ" : 0.208889,
        "VXUS" : 0.086667
      },
      "utility" : 0.16259697178269764,
      "delta" : 0.0013921147876794215
    }, {
      "symbol" : "VXUS",
      "weights" : {
        "USO" : 0.097778,
        "GLD" : 0.086667,
        "MUB" : 0.086667,
        "VCLT" : 0.086667,
        "LQD" : 0.086667,
        "IGLB" : 0.086667,
        "XOM" : 0.086667,
        "SPY" : 0.086667,
        "QQQ" : 0.197778,
        "VXUS" : 0.097778
      },
      "utility" : 0.1609448045590414,
      "delta" : -2.600524359768208E-4
    } ],
    "winner" : "QQQ",
    "endWeights" : {
      "USO" : 0.097778,
      "GLD" : 0.086667,
      "MUB" : 0.086667,
      "VCLT" : 0.086667,
      "LQD" : 0.086667,
      "IGLB" : 0.086667,
      "XOM" : 0.086667,
      "SPY" : 0.086667,
      "QQQ" : 0.208889,
      "VXUS" : 0.086667
    },
    "endUtility" : 0.16259697178269764,
    "improvement" : 0.0013921147876794215
  }, {
    "epoch" : 12,
    "startWeights" : {
      "USO" : 0.097778,
      "GLD" : 0.086667,
      "MUB" : 0.086667,
      "VCLT" : 0.086667,
      "LQD" : 0.086667,
      "IGLB" : 0.086667,
      "XOM" : 0.086667,
      "SPY" : 0.086667,
      "QQQ" : 0.208889,
      "VXUS" : 0.086667
    },
    "startUtility" : 0.16259697178269764,
    "feasibleCount" : 10,
    "variants" : [ {
      "symbol" : "USO",
      "weights" : {
        "USO" : 0.107778,
        "GLD" : 0.085556,
        "MUB" : 0.085556,
        "VCLT" : 0.085556,
        "LQD" : 0.085556,
        "IGLB" : 0.085556,
        "XOM" : 0.085556,
        "SPY" : 0.085556,
        "QQQ" : 0.207778,
        "VXUS" : 0.085556
      },
      "utility" : 0.1639089502970883,
      "delta" : 0.0013119785143906604
    }, {
      "symbol" : "GLD",
      "weights" : {
        "USO" : 0.096667,
        "GLD" : 0.096667,
        "MUB" : 0.085556,
        "VCLT" : 0.085556,
        "LQD" : 0.085556,
        "IGLB" : 0.085556,
        "XOM" : 0.085556,
        "SPY" : 0.085556,
        "QQQ" : 0.207778,
        "VXUS" : 0.085556
      },
      "utility" : 0.16347215377900776,
      "delta" : 8.751819963101204E-4
    }, {
      "symbol" : "MUB",
      "weights" : {
        "USO" : 0.096667,
        "GLD" : 0.085556,
        "MUB" : 0.096667,
        "VCLT" : 0.085556,
        "LQD" : 0.085556,
        "IGLB" : 0.085556,
        "XOM" : 0.085556,
        "SPY" : 0.085556,
        "QQQ" : 0.207778,
        "VXUS" : 0.085556
      },
      "utility" : 0.16125417649810636,
      "delta" : -0.001342795284591275
    }, {
      "symbol" : "VCLT",
      "weights" : {
        "USO" : 0.096667,
        "GLD" : 0.085556,
        "MUB" : 0.085556,
        "VCLT" : 0.096667,
        "LQD" : 0.085556,
        "IGLB" : 0.085556,
        "XOM" : 0.085556,
        "SPY" : 0.085556,
        "QQQ" : 0.207778,
        "VXUS" : 0.085556
      },
      "utility" : 0.16131747838368737,
      "delta" : -0.001279493399010262
    }, {
      "symbol" : "LQD",
      "weights" : {
        "USO" : 0.096667,
        "GLD" : 0.085556,
        "MUB" : 0.085556,
        "VCLT" : 0.085556,
        "LQD" : 0.096667,
        "IGLB" : 0.085556,
        "XOM" : 0.085556,
        "SPY" : 0.085556,
        "QQQ" : 0.207778,
        "VXUS" : 0.085556
      },
      "utility" : 0.16134177352659904,
      "delta" : -0.0012551982560985997
    }, {
      "symbol" : "IGLB",
      "weights" : {
        "USO" : 0.096667,
        "GLD" : 0.085556,
        "MUB" : 0.085556,
        "VCLT" : 0.085556,
        "LQD" : 0.085556,
        "IGLB" : 0.096667,
        "XOM" : 0.085556,
        "SPY" : 0.085556,
        "QQQ" : 0.207778,
        "VXUS" : 0.085556
      },
      "utility" : 0.1613067998202119,
      "delta" : -0.0012901719624857366
    }, {
      "symbol" : "XOM",
      "weights" : {
        "USO" : 0.096667,
        "GLD" : 0.085556,
        "MUB" : 0.085556,
        "VCLT" : 0.085556,
        "LQD" : 0.085556,
        "IGLB" : 0.085556,
        "XOM" : 0.096667,
        "SPY" : 0.085556,
        "QQQ" : 0.207778,
        "VXUS" : 0.085556
      },
      "utility" : 0.16374472895435518,
      "delta" : 0.0011477571716575485
    }, {
      "symbol" : "SPY",
      "weights" : {
        "USO" : 0.096667,
        "GLD" : 0.085556,
        "MUB" : 0.085556,
        "VCLT" : 0.085556,
        "LQD" : 0.085556,
        "IGLB" : 0.085556,
        "XOM" : 0.085556,
        "SPY" : 0.096667,
        "QQQ" : 0.207778,
        "VXUS" : 0.085556
      },
      "utility" : 0.16313221068299977,
      "delta" : 5.352389003021318E-4
    }, {
      "symbol" : "QQQ",
      "weights" : {
        "USO" : 0.096667,
        "GLD" : 0.085556,
        "MUB" : 0.085556,
        "VCLT" : 0.085556,
        "LQD" : 0.085556,
        "IGLB" : 0.085556,
        "XOM" : 0.085556,
        "SPY" : 0.085556,
        "QQQ" : 0.218889,
        "VXUS" : 0.085556
      },
      "utility" : 0.16393423370779261,
      "delta" : 0.001337261925094979
    }, {
      "symbol" : "VXUS",
      "weights" : {
        "USO" : 0.096667,
        "GLD" : 0.085556,
        "MUB" : 0.085556,
        "VCLT" : 0.085556,
        "LQD" : 0.085556,
        "IGLB" : 0.085556,
        "XOM" : 0.085556,
        "SPY" : 0.085556,
        "QQQ" : 0.207778,
        "VXUS" : 0.096667
      },
      "utility" : 0.16231021675442117,
      "delta" : -2.8675502827646415E-4
    } ],
    "winner" : "QQQ",
    "endWeights" : {
      "USO" : 0.096667,
      "GLD" : 0.085556,
      "MUB" : 0.085556,
      "VCLT" : 0.085556,
      "LQD" : 0.085556,
      "IGLB" : 0.085556,
      "XOM" : 0.085556,
      "SPY" : 0.085556,
      "QQQ" : 0.218889,
      "VXUS" : 0.085556
    },
    "endUtility" : 0.16393423370779261,
    "improvement" : 0.001337261925094979
  }, {
    "epoch" : 13,
    "startWeights" : {
      "USO" : 0.096667,
      "GLD" : 0.085556,
      "MUB" : 0.085556,
      "VCLT" : 0.085556,
      "LQD" : 0.085556,
      "IGLB" : 0.085556,
      "XOM" : 0.085556,
      "SPY" : 0.085556,
      "QQQ" : 0.218889,
      "VXUS" : 0.085556
    },
    "startUtility" : 0.16393423370779261,
    "feasibleCount" : 10,
    "variants" : [ {
      "symbol" : "USO",
      "weights" : {
        "USO" : 0.106667,
        "GLD" : 0.084444,
        "MUB" : 0.084444,
        "VCLT" : 0.084444,
        "LQD" : 0.084444,
        "IGLB" : 0.084444,
        "XOM" : 0.084444,
        "SPY" : 0.084444,
        "QQQ" : 0.217778,
        "VXUS" : 0.084444
      },
      "utility" : 0.16529344309267363,
      "delta" : 0.001359209384881016
    }, {
      "symbol" : "GLD",
      "weights" : {
        "USO" : 0.095556,
        "GLD" : 0.095556,
        "MUB" : 0.084444,
        "VCLT" : 0.084444,
        "LQD" : 0.084444,
        "IGLB" : 0.084444,
        "XOM" : 0.084444,
        "SPY" : 0.084444,
        "QQQ" : 0.217778,
        "VXUS" : 0.084444
      },
      "utility" : 0.1648116540738113,
      "delta" : 8.774203660186775E-4
    }, {
      "symbol" : "MUB",
      "weights" : {
        "USO" : 0.095556,
        "GLD" : 0.084444,
        "MUB" : 0.095556,
        "VCLT" : 0.084444,
        "LQD" : 0.084444,
        "IGLB" : 0.084444,
        "XOM" : 0.084444,
        "SPY" : 0.084444,
        "QQQ" : 0.217778,
        "VXUS" : 0.084444
      },
      "utility" : 0.16258815223685505,
      "delta" : -0.0013460814709375657
    }, {
      "symbol" : "VCLT",
      "weights" : {
        "USO" : 0.095556,
        "GLD" : 0.084444,
        "MUB" : 0.084444,
        "VCLT" : 0.095556,
        "LQD" : 0.084444,
        "IGLB" : 0.084444,
        "XOM" : 0.084444,
        "SPY" : 0.084444,
        "QQQ" : 0.217778,
        "VXUS" : 0.084444
      },
      "utility" : 0.16265734693023057,
      "delta" : -0.0012768867775620474
    }, {
      "symbol" : "LQD",
      "weights" : {
        "USO" : 0.095556,
        "GLD" : 0.084444,
        "MUB" : 0.084444,
        "VCLT" : 0.084444,
        "LQD" : 0.095556,
        "IGLB" : 0.084444,
        "XOM" : 0.084444,
        "SPY" : 0.084444,
        "QQQ" : 0.217778,
        "VXUS" : 0.084444
      },
      "utility" : 0.1626765584026898,
      "delta" : -0.0012576753051028178
    }, {
      "symbol" : "IGLB",
      "weights" : {
        "USO" : 0.095556,
        "GLD" : 0.084444,
        "MUB" : 0.084444,
        "VCLT" : 0.084444,
        "LQD" : 0.084444,
        "IGLB" : 0.095556,
        "XOM" : 0.084444,
        "SPY" : 0.084444,
        "QQQ" : 0.217778,
        "VXUS" : 0.084444
      },
      "utility" : 0.16264697131370975,
      "delta" : -0.001287262394082861
    }, {
      "symbol" : "XOM",
      "weights" : {
        "USO" : 0.095556,
        "GLD" : 0.084444,
        "MUB" : 0.084444,
        "VCLT" : 0.084444,
        "LQD" : 0.084444,
        "IGLB" : 0.084444,
        "XOM" : 0.095556,
        "SPY" : 0.084444,
        "QQQ" : 0.217778,
        "VXUS" : 0.084444
      },
      "utility" : 0.16515090840031454,
      "delta" : 0.0012166746925219296
    }, {
      "symbol" : "SPY",
      "weights" : {
        "USO" : 0.095556,
        "GLD" : 0.084444,
        "MUB" : 0.084444,
        "VCLT" : 0.084444,
        "LQD" : 0.084444,
        "IGLB" : 0.084444,
        "XOM" : 0.084444,
        "SPY" : 0.095556,
        "QQQ" : 0.217778,
        "VXUS" : 0.084444
      },
      "utility" : 0.16445569555925402,
      "delta" : 5.214618514614022E-4
    }, {
      "symbol" : "QQQ",
      "weights" : {
        "USO" : 0.095556,
        "GLD" : 0.084444,
        "MUB" : 0.084444,
        "VCLT" : 0.084444,
        "LQD" : 0.084444,
        "IGLB" : 0.084444,
        "XOM" : 0.084444,
        "SPY" : 0.084444,
        "QQQ" : 0.228889,
        "VXUS" : 0.084444
      },
      "utility" : 0.16524363508208612,
      "delta" : 0.0013094013742935007
    }, {
      "symbol" : "VXUS",
      "weights" : {
        "USO" : 0.095556,
        "GLD" : 0.084444,
        "MUB" : 0.084444,
        "VCLT" : 0.084444,
        "LQD" : 0.084444,
        "IGLB" : 0.084444,
        "XOM" : 0.084444,
        "SPY" : 0.084444,
        "QQQ" : 0.217778,
        "VXUS" : 0.095556
      },
      "utility" : 0.16364829138258727,
      "delta" : -2.859423252053461E-4
    } ],
    "winner" : "USO",
    "endWeights" : {
      "USO" : 0.106667,
      "GLD" : 0.084444,
      "MUB" : 0.084444,
      "VCLT" : 0.084444,
      "LQD" : 0.084444,
      "IGLB" : 0.084444,
      "XOM" : 0.084444,
      "SPY" : 0.084444,
      "QQQ" : 0.217778,
      "VXUS" : 0.084444
    },
    "endUtility" : 0.16529344309267363,
    "improvement" : 0.001359209384881016
  }, {
    "epoch" : 14,
    "startWeights" : {
      "USO" : 0.106667,
      "GLD" : 0.084444,
      "MUB" : 0.084444,
      "VCLT" : 0.084444,
      "LQD" : 0.084444,
      "IGLB" : 0.084444,
      "XOM" : 0.084444,
      "SPY" : 0.084444,
      "QQQ" : 0.217778,
      "VXUS" : 0.084444
    },
    "startUtility" : 0.16529344309267363,
    "feasibleCount" : 10,
    "variants" : [ {
      "symbol" : "USO",
      "weights" : {
        "USO" : 0.116667,
        "GLD" : 0.083333,
        "MUB" : 0.083333,
        "VCLT" : 0.083333,
        "LQD" : 0.083333,
        "IGLB" : 0.083333,
        "XOM" : 0.083333,
        "SPY" : 0.083333,
        "QQQ" : 0.216667,
        "VXUS" : 0.083333
      },
      "utility" : 0.16650432342181978,
      "delta" : 0.0012108803291461523
    }, {
      "symbol" : "GLD",
      "weights" : {
        "USO" : 0.105556,
        "GLD" : 0.094444,
        "MUB" : 0.083333,
        "VCLT" : 0.083333,
        "LQD" : 0.083333,
        "IGLB" : 0.083333,
        "XOM" : 0.083333,
        "SPY" : 0.083333,
        "QQQ" : 0.216667,
        "VXUS" : 0.083333
      },
      "utility" : 0.16618260539866245,
      "delta" : 8.891623059888165E-4
    }, {
      "symbol" : "MUB",
      "weights" : {
        "USO" : 0.105556,
        "GLD" : 0.083333,
        "MUB" : 0.094444,
        "VCLT" : 0.083333,
        "LQD" : 0.083333,
        "IGLB" : 0.083333,
        "XOM" : 0.083333,
        "SPY" : 0.083333,
        "QQQ" : 0.216667,
        "VXUS" : 0.083333
      },
      "utility" : 0.16397025712695962,
      "delta" : -0.0013231859657140133
    }, {
      "symbol" : "VCLT",
      "weights" : {
        "USO" : 0.105556,
        "GLD" : 0.083333,
        "MUB" : 0.083333,
        "VCLT" : 0.094444,
        "LQD" : 0.083333,
        "IGLB" : 0.083333,
        "XOM" : 0.083333,
        "SPY" : 0.083333,
        "QQQ" : 0.216667,
        "VXUS" : 0.083333
      },
      "utility" : 0.16406140283218276,
      "delta" : -0.0012320402604908687
    }, {
      "symbol" : "LQD",
      "weights" : {
        "USO" : 0.105556,
        "GLD" : 0.083333,
        "MUB" : 0.083333,
        "VCLT" : 0.083333,
        "LQD" : 0.094444,
        "IGLB" : 0.083333,
        "XOM" : 0.083333,
        "SPY" : 0.083333,
        "QQQ" : 0.216667,
        "VXUS" : 0.083333
      },
      "utility" : 0.16407297822928776,
      "delta" : -0.0012204648633858672
    }, {
      "symbol" : "IGLB",
      "weights" : {
        "USO" : 0.105556,
        "GLD" : 0.083333,
        "MUB" : 0.083333,
        "VCLT" : 0.083333,
        "LQD" : 0.083333,
        "IGLB" : 0.094444,
        "XOM" : 0.083333,
        "SPY" : 0.083333,
        "QQQ" : 0.216667,
        "VXUS" : 0.083333
      },
      "utility" : 0.16405041554773936,
      "delta" : -0.001243027544934272
    }, {
      "symbol" : "XOM",
      "weights" : {
        "USO" : 0.105556,
        "GLD" : 0.083333,
        "MUB" : 0.083333,
        "VCLT" : 0.083333,
        "LQD" : 0.083333,
        "IGLB" : 0.083333,
        "XOM" : 0.094444,
        "SPY" : 0.083333,
        "QQQ" : 0.216667,
        "VXUS" : 0.083333
      },
      "utility" : 0.16640821777290374,
      "delta" : 0.0011147746802301073
    }, {
      "symbol" : "SPY",
      "weights" : {
        "USO" : 0.105556,
        "GLD" : 0.083333,
        "MUB" : 0.083333,
        "VCLT" : 0.083333,
        "LQD" : 0.083333,
        "IGLB" : 0.083333,
        "XOM" : 0.083333,
        "SPY" : 0.094444,
        "QQQ" : 0.216667,
        "VXUS" : 0.083333
      },
      "utility" : 0.16583879700970225,
      "delta" : 5.453539170286181E-4
    }, {
      "symbol" : "QQQ",
      "weights" : {
        "USO" : 0.105556,
        "GLD" : 0.083333,
        "MUB" : 0.083333,
        "VCLT" : 0.083333,
        "LQD" : 0.083333,
        "IGLB" : 0.083333,
        "XOM" : 0.083333,
        "SPY" : 0.083333,
        "QQQ" : 0.227778,
        "VXUS" : 0.083333
      },
      "utility" : 0.16665405894043156,
      "delta" : 0.0013606158477579289
    }, {
      "symbol" : "VXUS",
      "weights" : {
        "USO" : 0.105556,
        "GLD" : 0.083333,
        "MUB" : 0.083333,
        "VCLT" : 0.083333,
        "LQD" : 0.083333,
        "IGLB" : 0.083333,
        "XOM" : 0.083333,
        "SPY" : 0.083333,
        "QQQ" : 0.216667,
        "VXUS" : 0.094444
      },
      "utility" : 0.16503496810949858,
      "delta" : -2.584749831750499E-4
    } ],
    "winner" : "QQQ",
    "endWeights" : {
      "USO" : 0.105556,
      "GLD" : 0.083333,
      "MUB" : 0.083333,
      "VCLT" : 0.083333,
      "LQD" : 0.083333,
      "IGLB" : 0.083333,
      "XOM" : 0.083333,
      "SPY" : 0.083333,
      "QQQ" : 0.227778,
      "VXUS" : 0.083333
    },
    "endUtility" : 0.16665405894043156,
    "improvement" : 0.0013606158477579289
  }, {
    "epoch" : 15,
    "startWeights" : {
      "USO" : 0.105556,
      "GLD" : 0.083333,
      "MUB" : 0.083333,
      "VCLT" : 0.083333,
      "LQD" : 0.083333,
      "IGLB" : 0.083333,
      "XOM" : 0.083333,
      "SPY" : 0.083333,
      "QQQ" : 0.227778,
      "VXUS" : 0.083333
    },
    "startUtility" : 0.16665405894043156,
    "feasibleCount" : 10,
    "variants" : [ {
      "symbol" : "USO",
      "weights" : {
        "USO" : 0.115556,
        "GLD" : 0.082222,
        "MUB" : 0.082222,
        "VCLT" : 0.082222,
        "LQD" : 0.082222,
        "IGLB" : 0.082222,
        "XOM" : 0.082222,
        "SPY" : 0.082222,
        "QQQ" : 0.226667,
        "VXUS" : 0.082222
      },
      "utility" : 0.16791765228906363,
      "delta" : 0.001263593348632075
    }, {
      "symbol" : "GLD",
      "weights" : {
        "USO" : 0.104444,
        "GLD" : 0.093333,
        "MUB" : 0.082222,
        "VCLT" : 0.082222,
        "LQD" : 0.082222,
        "IGLB" : 0.082222,
        "XOM" : 0.082222,
        "SPY" : 0.082222,
        "QQQ" : 0.226667,
        "VXUS" : 0.082222
      },
      "utility" : 0.167536838358105,
      "delta" : 8.827794176734516E-4
    }, {
      "symbol" : "MUB",
      "weights" : {
        "USO" : 0.104444,
        "GLD" : 0.082222,
        "MUB" : 0.093333,
        "VCLT" : 0.082222,
        "LQD" : 0.082222,
        "IGLB" : 0.082222,
        "XOM" : 0.082222,
        "SPY" : 0.082222,
        "QQQ" : 0.226667,
        "VXUS" : 0.082222
      },
      "utility" : 0.16532571884081645,
      "delta" : -0.0013283400996151051
    }, {
      "symbol" : "VCLT",
      "weights" : {
        "USO" : 0.104444,
        "GLD" : 0.082222,
        "MUB" : 0.082222,
        "VCLT" : 0.093333,
        "LQD" : 0.082222,
        "IGLB" : 0.082222,
        "XOM" : 0.082222,
        "SPY" : 0.082222,
        "QQQ" : 0.226667,
        "VXUS" : 0.082222
      },
      "utility" : 0.1654077459198281,
      "delta" : -0.0012463130206034623
    }, {
      "symbol" : "LQD",
      "weights" : {
        "USO" : 0.104444,
        "GLD" : 0.082222,
        "MUB" : 0.082222,
        "VCLT" : 0.082222,
        "LQD" : 0.093333,
        "IGLB" : 0.082222,
        "XOM" : 0.082222,
        "SPY" : 0.082222,
        "QQQ" : 0.226667,
        "VXUS" : 0.082222
      },
      "utility" : 0.16542122624403416,
      "delta" : -0.0012328326963974012
    }, {
      "symbol" : "IGLB",
      "weights" : {
        "USO" : 0.104444,
        "GLD" : 0.082222,
        "MUB" : 0.082222,
        "VCLT" : 0.082222,
        "LQD" : 0.082222,
        "IGLB" : 0.093333,
        "XOM" : 0.082222,
        "SPY" : 0.082222,
        "QQQ" : 0.226667,
        "VXUS" : 0.082222
      },
      "utility" : 0.1653969686115634,
      "delta" : -0.0012570903288681712
    }, {
      "symbol" : "XOM",
      "weights" : {
        "USO" : 0.104444,
        "GLD" : 0.082222,
        "MUB" : 0.082222,
        "VCLT" : 0.082222,
        "LQD" : 0.082222,
        "IGLB" : 0.082222,
        "XOM" : 0.093333,
        "SPY" : 0.082222,
        "QQQ" : 0.226667,
        "VXUS" : 0.082222
      },
      "utility" : 0.16781135684785767,
      "delta" : 0.001157297907426108
    }, {
      "symbol" : "SPY",
      "weights" : {
        "USO" : 0.104444,
        "GLD" : 0.082222,
        "MUB" : 0.082222,
        "VCLT" : 0.082222,
        "LQD" : 0.082222,
        "IGLB" : 0.082222,
        "XOM" : 0.082222,
        "SPY" : 0.093333,
        "QQQ" : 0.226667,
        "VXUS" : 0.082222
      },
      "utility" : 0.16718357308684276,
      "delta" : 5.295141464111974E-4
    }, {
      "symbol" : "QQQ",
      "weights" : {
        "USO" : 0.104444,
        "GLD" : 0.082222,
        "MUB" : 0.082222,
        "VCLT" : 0.082222,
        "LQD" : 0.082222,
        "IGLB" : 0.082222,
        "XOM" : 0.082222,
        "SPY" : 0.082222,
        "QQQ" : 0.237778,
        "VXUS" : 0.082222
      },
      "utility" : 0.16797536690238482,
      "delta" : 0.0013213079619532608
    }, {
      "symbol" : "VXUS",
      "weights" : {
        "USO" : 0.104444,
        "GLD" : 0.082222,
        "MUB" : 0.082222,
        "VCLT" : 0.082222,
        "LQD" : 0.082222,
        "IGLB" : 0.082222,
        "XOM" : 0.082222,
        "SPY" : 0.082222,
        "QQQ" : 0.226667,
        "VXUS" : 0.093333
      },
      "utility" : 0.1663804599757236,
      "delta" : -2.735989647079662E-4
    } ],
    "winner" : "QQQ",
    "endWeights" : {
      "USO" : 0.104444,
      "GLD" : 0.082222,
      "MUB" : 0.082222,
      "VCLT" : 0.082222,
      "LQD" : 0.082222,
      "IGLB" : 0.082222,
      "XOM" : 0.082222,
      "SPY" : 0.082222,
      "QQQ" : 0.237778,
      "VXUS" : 0.082222
    },
    "endUtility" : 0.16797536690238482,
    "improvement" : 0.0013213079619532608
  }, {
    "epoch" : 16,
    "startWeights" : {
      "USO" : 0.104444,
      "GLD" : 0.082222,
      "MUB" : 0.082222,
      "VCLT" : 0.082222,
      "LQD" : 0.082222,
      "IGLB" : 0.082222,
      "XOM" : 0.082222,
      "SPY" : 0.082222,
      "QQQ" : 0.237778,
      "VXUS" : 0.082222
    },
    "startUtility" : 0.16797536690238482,
    "feasibleCount" : 10,
    "variants" : [ {
      "symbol" : "USO",
      "weights" : {
        "USO" : 0.114444,
        "GLD" : 0.081111,
        "MUB" : 0.081111,
        "VCLT" : 0.081111,
        "LQD" : 0.081111,
        "IGLB" : 0.081111,
        "XOM" : 0.081111,
        "SPY" : 0.081111,
        "QQQ" : 0.236667,
        "VXUS" : 0.081111
      },
      "utility" : 0.16929705863411296,
      "delta" : 0.0013216917317281363
    }, {
      "symbol" : "GLD",
      "weights" : {
        "USO" : 0.103333,
        "GLD" : 0.092222,
        "MUB" : 0.081111,
        "VCLT" : 0.081111,
        "LQD" : 0.081111,
        "IGLB" : 0.081111,
        "XOM" : 0.081111,
        "SPY" : 0.081111,
        "QQQ" : 0.236667,
        "VXUS" : 0.081111
      },
      "utility" : 0.16885663153473587,
      "delta" : 8.812646323510531E-4
    }, {
      "symbol" : "MUB",
      "weights" : {
        "USO" : 0.103333,
        "GLD" : 0.081111,
        "MUB" : 0.092222,
        "VCLT" : 0.081111,
        "LQD" : 0.081111,
        "IGLB" : 0.081111,
        "XOM" : 0.081111,
        "SPY" : 0.081111,
        "QQQ" : 0.236667,
        "VXUS" : 0.081111
      },
      "utility" : 0.1666383094999994,
      "delta" : -0.0013370574023854331
    }, {
      "symbol" : "VCLT",
      "weights" : {
        "USO" : 0.103333,
        "GLD" : 0.081111,
        "MUB" : 0.081111,
        "VCLT" : 0.092222,
        "LQD" : 0.081111,
        "IGLB" : 0.081111,
        "XOM" : 0.081111,
        "SPY" : 0.081111,
        "QQQ" : 0.236667,
        "VXUS" : 0.081111
      },
      "utility" : 0.16671996731706232,
      "delta" : -0.001255399585322503
    }, {
      "symbol" : "LQD",
      "weights" : {
        "USO" : 0.103333,
        "GLD" : 0.081111,
        "MUB" : 0.081111,
        "VCLT" : 0.081111,
        "LQD" : 0.092222,
        "IGLB" : 0.081111,
        "XOM" : 0.081111,
        "SPY" : 0.081111,
        "QQQ" : 0.236667,
        "VXUS" : 0.081111
      },
      "utility" : 0.16673346638987038,
      "delta" : -0.0012419005125144378
    }, {
      "symbol" : "IGLB",
      "weights" : {
        "USO" : 0.103333,
        "GLD" : 0.081111,
        "MUB" : 0.081111,
        "VCLT" : 0.081111,
        "LQD" : 0.081111,
        "IGLB" : 0.092222,
        "XOM" : 0.081111,
        "SPY" : 0.081111,
        "QQQ" : 0.236667,
        "VXUS" : 0.081111
      },
      "utility" : 0.16670924346572472,
      "delta" : -0.0012661234366601049
    }, {
      "symbol" : "XOM",
      "weights" : {
        "USO" : 0.103333,
        "GLD" : 0.081111,
        "MUB" : 0.081111,
        "VCLT" : 0.081111,
        "LQD" : 0.081111,
        "IGLB" : 0.081111,
        "XOM" : 0.092222,
        "SPY" : 0.081111,
        "QQQ" : 0.236667,
        "VXUS" : 0.081111
      },
      "utility" : 0.16918493187994194,
      "delta" : 0.001209564977557115
    }, {
      "symbol" : "SPY",
      "weights" : {
        "USO" : 0.103333,
        "GLD" : 0.081111,
        "MUB" : 0.081111,
        "VCLT" : 0.081111,
        "LQD" : 0.081111,
        "IGLB" : 0.081111,
        "XOM" : 0.081111,
        "SPY" : 0.092222,
        "QQQ" : 0.236667,
        "VXUS" : 0.081111
      },
      "utility" : 0.1684756971002169,
      "delta" : 5.003301978320773E-4
    }, {
      "symbol" : "QQQ",
      "weights" : {
        "USO" : 0.103333,
        "GLD" : 0.081111,
        "MUB" : 0.081111,
        "VCLT" : 0.081111,
        "LQD" : 0.081111,
        "IGLB" : 0.081111,
        "XOM" : 0.081111,
        "SPY" : 0.081111,
        "QQQ" : 0.247778,
        "VXUS" : 0.081111
      },
      "utility" : 0.16925150901091024,
      "delta" : 0.0012761421085254188
    }, {
      "symbol" : "VXUS",
      "weights" : {
        "USO" : 0.103333,
        "GLD" : 0.081111,
        "MUB" : 0.081111,
        "VCLT" : 0.081111,
        "LQD" : 0.081111,
        "IGLB" : 0.081111,
        "XOM" : 0.081111,
        "SPY" : 0.081111,
        "QQQ" : 0.236667,
        "VXUS" : 0.092222
      },
      "utility" : 0.16768090641779743,
      "delta" : -2.944604845873944E-4
    } ],
    "winner" : "USO",
    "endWeights" : {
      "USO" : 0.114444,
      "GLD" : 0.081111,
      "MUB" : 0.081111,
      "VCLT" : 0.081111,
      "LQD" : 0.081111,
      "IGLB" : 0.081111,
      "XOM" : 0.081111,
      "SPY" : 0.081111,
      "QQQ" : 0.236667,
      "VXUS" : 0.081111
    },
    "endUtility" : 0.16929705863411296,
    "improvement" : 0.0013216917317281363
  }, {
    "epoch" : 17,
    "startWeights" : {
      "USO" : 0.114444,
      "GLD" : 0.081111,
      "MUB" : 0.081111,
      "VCLT" : 0.081111,
      "LQD" : 0.081111,
      "IGLB" : 0.081111,
      "XOM" : 0.081111,
      "SPY" : 0.081111,
      "QQQ" : 0.236667,
      "VXUS" : 0.081111
    },
    "startUtility" : 0.16929705863411296,
    "feasibleCount" : 10,
    "variants" : [ {
      "symbol" : "USO",
      "weights" : {
        "USO" : 0.124444,
        "GLD" : 0.08,
        "MUB" : 0.08,
        "VCLT" : 0.08,
        "LQD" : 0.08,
        "IGLB" : 0.08,
        "XOM" : 0.08,
        "SPY" : 0.08,
        "QQQ" : 0.235556,
        "VXUS" : 0.08
      },
      "utility" : 0.17046172202979964,
      "delta" : 0.001164663395686688
    }, {
      "symbol" : "GLD",
      "weights" : {
        "USO" : 0.113333,
        "GLD" : 0.091111,
        "MUB" : 0.08,
        "VCLT" : 0.08,
        "LQD" : 0.08,
        "IGLB" : 0.08,
        "XOM" : 0.08,
        "SPY" : 0.08,
        "QQQ" : 0.235556,
        "VXUS" : 0.08
      },
      "utility" : 0.17018401711891248,
      "delta" : 8.869584847995271E-4
    }, {
      "symbol" : "MUB",
      "weights" : {
        "USO" : 0.113333,
        "GLD" : 0.08,
        "MUB" : 0.091111,
        "VCLT" : 0.08,
        "LQD" : 0.08,
        "IGLB" : 0.08,
        "XOM" : 0.08,
        "SPY" : 0.08,
        "QQQ" : 0.235556,
        "VXUS" : 0.08
      },
      "utility" : 0.16798257933043423,
      "delta" : -0.0013144793036787283
    }, {
      "symbol" : "VCLT",
      "weights" : {
        "USO" : 0.113333,
        "GLD" : 0.08,
        "MUB" : 0.08,
        "VCLT" : 0.091111,
        "LQD" : 0.08,
        "IGLB" : 0.08,
        "XOM" : 0.08,
        "SPY" : 0.08,
        "QQQ" : 0.235556,
        "VXUS" : 0.08
      },
      "utility" : 0.16809042153358353,
      "delta" : -0.0012066371005294285
    }, {
      "symbol" : "LQD",
      "weights" : {
        "USO" : 0.113333,
        "GLD" : 0.08,
        "MUB" : 0.08,
        "VCLT" : 0.08,
        "LQD" : 0.091111,
        "IGLB" : 0.08,
        "XOM" : 0.08,
        "SPY" : 0.08,
        "QQQ" : 0.235556,
        "VXUS" : 0.08
      },
      "utility" : 0.1680897457846615,
      "delta" : -0.0012073128494514695
    }, {
      "symbol" : "IGLB",
      "weights" : {
        "USO" : 0.113333,
        "GLD" : 0.08,
        "MUB" : 0.08,
        "VCLT" : 0.08,
        "LQD" : 0.08,
        "IGLB" : 0.091111,
        "XOM" : 0.08,
        "SPY" : 0.08,
        "QQQ" : 0.235556,
        "VXUS" : 0.08
      },
      "utility" : 0.16807886589849838,
      "delta" : -0.001218192735614576
    }, {
      "symbol" : "XOM",
      "weights" : {
        "USO" : 0.113333,
        "GLD" : 0.08,
        "MUB" : 0.08,
        "VCLT" : 0.08,
        "LQD" : 0.08,
        "IGLB" : 0.08,
        "XOM" : 0.091111,
        "SPY" : 0.08,
        "QQQ" : 0.235556,
        "VXUS" : 0.08
      },
      "utility" : 0.17042025821970638,
      "delta" : 0.0011231995855934263
    }, {
      "symbol" : "SPY",
      "weights" : {
        "USO" : 0.113333,
        "GLD" : 0.08,
        "MUB" : 0.08,
        "VCLT" : 0.08,
        "LQD" : 0.08,
        "IGLB" : 0.08,
        "XOM" : 0.08,
        "SPY" : 0.091111,
        "QQQ" : 0.235556,
        "VXUS" : 0.08
      },
      "utility" : 0.16981789826867424,
      "delta" : 5.208396345612876E-4
    }, {
      "symbol" : "QQQ",
      "weights" : {
        "USO" : 0.113333,
        "GLD" : 0.08,
        "MUB" : 0.08,
        "VCLT" : 0.08,
        "LQD" : 0.08,
        "IGLB" : 0.08,
        "XOM" : 0.08,
        "SPY" : 0.08,
        "QQQ" : 0.246667,
        "VXUS" : 0.08
      },
      "utility" : 0.17062719130006826,
      "delta" : 0.0013301326659553026
    }, {
      "symbol" : "VXUS",
      "weights" : {
        "USO" : 0.113333,
        "GLD" : 0.08,
        "MUB" : 0.08,
        "VCLT" : 0.08,
        "LQD" : 0.08,
        "IGLB" : 0.08,
        "XOM" : 0.08,
        "SPY" : 0.08,
        "QQQ" : 0.235556,
        "VXUS" : 0.091111
      },
      "utility" : 0.16902739568480163,
      "delta" : -2.6966294931132784E-4
    } ],
    "winner" : "QQQ",
    "endWeights" : {
      "USO" : 0.113333,
      "GLD" : 0.08,
      "MUB" : 0.08,
      "VCLT" : 0.08,
      "LQD" : 0.08,
      "IGLB" : 0.08,
      "XOM" : 0.08,
      "SPY" : 0.08,
      "QQQ" : 0.246667,
      "VXUS" : 0.08
    },
    "endUtility" : 0.17062719130006826,
    "improvement" : 0.0013301326659553026
  }, {
    "epoch" : 18,
    "startWeights" : {
      "USO" : 0.113333,
      "GLD" : 0.08,
      "MUB" : 0.08,
      "VCLT" : 0.08,
      "LQD" : 0.08,
      "IGLB" : 0.08,
      "XOM" : 0.08,
      "SPY" : 0.08,
      "QQQ" : 0.246667,
      "VXUS" : 0.08
    },
    "startUtility" : 0.17062719130006826,
    "feasibleCount" : 10,
    "variants" : [ {
      "symbol" : "USO",
      "weights" : {
        "USO" : 0.123333,
        "GLD" : 0.078889,
        "MUB" : 0.078889,
        "VCLT" : 0.078889,
        "LQD" : 0.078889,
        "IGLB" : 0.078889,
        "XOM" : 0.078889,
        "SPY" : 0.078889,
        "QQQ" : 0.245556,
        "VXUS" : 0.078889
      },
      "utility" : 0.17183954139767446,
      "delta" : 0.0012123500976062018
    }, {
      "symbol" : "GLD",
      "weights" : {
        "USO" : 0.112222,
        "GLD" : 0.09,
        "MUB" : 0.078889,
        "VCLT" : 0.078889,
        "LQD" : 0.078889,
        "IGLB" : 0.078889,
        "XOM" : 0.078889,
        "SPY" : 0.078889,
        "QQQ" : 0.245556,
        "VXUS" : 0.078889
      },
      "utility" : 0.17150814127744177,
      "delta" : 8.809499773735074E-4
    }, {
      "symbol" : "MUB",
      "weights" : {
        "USO" : 0.112222,
        "GLD" : 0.078889,
        "MUB" : 0.09,
        "VCLT" : 0.078889,
        "LQD" : 0.078889,
        "IGLB" : 0.078889,
        "XOM" : 0.078889,
        "SPY" : 0.078889,
        "QQQ" : 0.245556,
        "VXUS" : 0.078889
      },
      "utility" : 0.16931313800984066,
      "delta" : -0.0013140532902276014
    }, {
      "symbol" : "VCLT",
      "weights" : {
        "USO" : 0.112222,
        "GLD" : 0.078889,
        "MUB" : 0.078889,
        "VCLT" : 0.09,
        "LQD" : 0.078889,
        "IGLB" : 0.078889,
        "XOM" : 0.078889,
        "SPY" : 0.078889,
        "QQQ" : 0.245556,
        "VXUS" : 0.078889
      },
      "utility" : 0.1694201470086287,
      "delta" : -0.0012070442914395574
    }, {
      "symbol" : "LQD",
      "weights" : {
        "USO" : 0.112222,
        "GLD" : 0.078889,
        "MUB" : 0.078889,
        "VCLT" : 0.078889,
        "LQD" : 0.09,
        "IGLB" : 0.078889,
        "XOM" : 0.078889,
        "SPY" : 0.078889,
        "QQQ" : 0.245556,
        "VXUS" : 0.078889
      },
      "utility" : 0.16942015860286092,
      "delta" : -0.0012070326972073442
    }, {
      "symbol" : "IGLB",
      "weights" : {
        "USO" : 0.112222,
        "GLD" : 0.078889,
        "MUB" : 0.078889,
        "VCLT" : 0.078889,
        "LQD" : 0.078889,
        "IGLB" : 0.09,
        "XOM" : 0.078889,
        "SPY" : 0.078889,
        "QQQ" : 0.245556,
        "VXUS" : 0.078889
      },
      "utility" : 0.16940958671732712,
      "delta" : -0.0012176045827411441
    }, {
      "symbol" : "XOM",
      "weights" : {
        "USO" : 0.112222,
        "GLD" : 0.078889,
        "MUB" : 0.078889,
        "VCLT" : 0.078889,
        "LQD" : 0.078889,
        "IGLB" : 0.078889,
        "XOM" : 0.09,
        "SPY" : 0.078889,
        "QQQ" : 0.245556,
        "VXUS" : 0.078889
      },
      "utility" : 0.17179078524912617,
      "delta" : 0.0011635939490579061
    }, {
      "symbol" : "SPY",
      "weights" : {
        "USO" : 0.112222,
        "GLD" : 0.078889,
        "MUB" : 0.078889,
        "VCLT" : 0.078889,
        "LQD" : 0.078889,
        "IGLB" : 0.078889,
        "XOM" : 0.078889,
        "SPY" : 0.09,
        "QQQ" : 0.245556,
        "VXUS" : 0.078889
      },
      "utility" : 0.17113009219358816,
      "delta" : 5.029008935198975E-4
    }, {
      "symbol" : "QQQ",
      "weights" : {
        "USO" : 0.112222,
        "GLD" : 0.078889,
        "MUB" : 0.078889,
        "VCLT" : 0.078889,
        "LQD" : 0.078889,
        "IGLB" : 0.078889,
        "XOM" : 0.078889,
        "SPY" : 0.078889,
        "QQQ" : 0.256667,
        "VXUS" : 0.078889
      },
      "utility" : 0.17192615666930258,
      "delta" : 0.0012989653692343228
    }, {
      "symbol" : "VXUS",
      "weights" : {
        "USO" : 0.112222,
        "GLD" : 0.078889,
        "MUB" : 0.078889,
        "VCLT" : 0.078889,
        "LQD" : 0.078889,
        "IGLB" : 0.078889,
        "XOM" : 0.078889,
        "SPY" : 0.078889,
        "QQQ" : 0.245556,
        "VXUS" : 0.09
      },
      "utility" : 0.17034977479621194,
      "delta" : -2.7741650385632033E-4
    } ],
    "winner" : "QQQ",
    "endWeights" : {
      "USO" : 0.112222,
      "GLD" : 0.078889,
      "MUB" : 0.078889,
      "VCLT" : 0.078889,
      "LQD" : 0.078889,
      "IGLB" : 0.078889,
      "XOM" : 0.078889,
      "SPY" : 0.078889,
      "QQQ" : 0.256667,
      "VXUS" : 0.078889
    },
    "endUtility" : 0.17192615666930258,
    "improvement" : 0.0012989653692343228
  }, {
    "epoch" : 19,
    "startWeights" : {
      "USO" : 0.112222,
      "GLD" : 0.078889,
      "MUB" : 0.078889,
      "VCLT" : 0.078889,
      "LQD" : 0.078889,
      "IGLB" : 0.078889,
      "XOM" : 0.078889,
      "SPY" : 0.078889,
      "QQQ" : 0.256667,
      "VXUS" : 0.078889
    },
    "startUtility" : 0.17192615666930258,
    "feasibleCount" : 10,
    "variants" : [ {
      "symbol" : "USO",
      "weights" : {
        "USO" : 0.122222,
        "GLD" : 0.077778,
        "MUB" : 0.077778,
        "VCLT" : 0.077778,
        "LQD" : 0.077778,
        "IGLB" : 0.077778,
        "XOM" : 0.077778,
        "SPY" : 0.077778,
        "QQQ" : 0.255556,
        "VXUS" : 0.077778
      },
      "utility" : 0.17315541529589037,
      "delta" : 0.0012292586265877925
    }, {
      "symbol" : "GLD",
      "weights" : {
        "USO" : 0.111111,
        "GLD" : 0.088889,
        "MUB" : 0.077778,
        "VCLT" : 0.077778,
        "LQD" : 0.077778,
        "IGLB" : 0.077778,
        "XOM" : 0.077778,
        "SPY" : 0.077778,
        "QQQ" : 0.255556,
        "VXUS" : 0.077778
      },
      "utility" : 0.1727965428392192,
      "delta" : 8.703861699166093E-4
    }, {
      "symbol" : "MUB",
      "weights" : {
        "USO" : 0.111111,
        "GLD" : 0.077778,
        "MUB" : 0.088889,
        "VCLT" : 0.077778,
        "LQD" : 0.077778,
        "IGLB" : 0.077778,
        "XOM" : 0.077778,
        "SPY" : 0.077778,
        "QQQ" : 0.255556,
        "VXUS" : 0.077778
      },
      "utility" : 0.17060539895916277,
      "delta" : -0.0013207577101398138
    }, {
      "symbol" : "VCLT",
      "weights" : {
        "USO" : 0.111111,
        "GLD" : 0.077778,
        "MUB" : 0.077778,
        "VCLT" : 0.088889,
        "LQD" : 0.077778,
        "IGLB" : 0.077778,
        "XOM" : 0.077778,
        "SPY" : 0.077778,
        "QQQ" : 0.255556,
        "VXUS" : 0.077778
      },
      "utility" : 0.1707080292210778,
      "delta" : -0.0012181274482247761
    }, {
      "symbol" : "LQD",
      "weights" : {
        "USO" : 0.111111,
        "GLD" : 0.077778,
        "MUB" : 0.077778,
        "VCLT" : 0.077778,
        "LQD" : 0.088889,
        "IGLB" : 0.077778,
        "XOM" : 0.077778,
        "SPY" : 0.077778,
        "QQQ" : 0.255556,
        "VXUS" : 0.077778
      },
      "utility" : 0.17071055234842894,
      "delta" : -0.0012156043208736422
    }, {
      "symbol" : "IGLB",
      "weights" : {
        "USO" : 0.111111,
        "GLD" : 0.077778,
        "MUB" : 0.077778,
        "VCLT" : 0.077778,
        "LQD" : 0.077778,
        "IGLB" : 0.088889,
        "XOM" : 0.077778,
        "SPY" : 0.077778,
        "QQQ" : 0.255556,
        "VXUS" : 0.077778
      },
      "utility" : 0.17069763422198764,
      "delta" : -0.0012285224473149448
    }, {
      "symbol" : "XOM",
      "weights" : {
        "USO" : 0.111111,
        "GLD" : 0.077778,
        "MUB" : 0.077778,
        "VCLT" : 0.077778,
        "LQD" : 0.077778,
        "IGLB" : 0.077778,
        "XOM" : 0.088889,
        "SPY" : 0.077778,
        "QQQ" : 0.255556,
        "VXUS" : 0.077778
      },
      "utility" : 0.17313076721647175,
      "delta" : 0.001204610547169166
    }, {
      "symbol" : "SPY",
      "weights" : {
        "USO" : 0.111111,
        "GLD" : 0.077778,
        "MUB" : 0.077778,
        "VCLT" : 0.077778,
        "LQD" : 0.077778,
        "IGLB" : 0.077778,
        "XOM" : 0.077778,
        "SPY" : 0.088889,
        "QQQ" : 0.255556,
        "VXUS" : 0.077778
      },
      "utility" : 0.1724003182022926,
      "delta" : 4.7416153299001396E-4
    }, {
      "symbol" : "QQQ",
      "weights" : {
        "USO" : 0.111111,
        "GLD" : 0.077778,
        "MUB" : 0.077778,
        "VCLT" : 0.077778,
        "LQD" : 0.077778,
        "IGLB" : 0.077778,
        "XOM" : 0.077778,
        "SPY" : 0.077778,
        "QQQ" : 0.266667,
        "VXUS" : 0.077778
      },
      "utility" : 0.1731738897293391,
      "delta" : 0.0012477330600365044
    }, {
      "symbol" : "VXUS",
      "weights" : {
        "USO" : 0.111111,
        "GLD" : 0.077778,
        "MUB" : 0.077778,
        "VCLT" : 0.077778,
        "LQD" : 0.077778,
        "IGLB" : 0.077778,
        "XOM" : 0.077778,
        "SPY" : 0.077778,
        "QQQ" : 0.255556,
        "VXUS" : 0.088889
      },
      "utility" : 0.17163778998688994,
      "delta" : -2.883666824126385E-4
    } ],
    "winner" : "QQQ",
    "endWeights" : {
      "USO" : 0.111111,
      "GLD" : 0.077778,
      "MUB" : 0.077778,
      "VCLT" : 0.077778,
      "LQD" : 0.077778,
      "IGLB" : 0.077778,
      "XOM" : 0.077778,
      "SPY" : 0.077778,
      "QQQ" : 0.266667,
      "VXUS" : 0.077778
    },
    "endUtility" : 0.1731738897293391,
    "improvement" : 0.0012477330600365044
  } ],
  "finalUtility" : 0.1731738897293391,
  "totalGain" : 0.02882910591973631,
  "epochCount" : 20
}